Workbook

Sheet 任务列表
A1: 序号 | B1: 任务key | C1: 任务名称 | D1: 难度 | E1: 战斗类型 | F1: 防守任务 | G1: 仅门客 | H1: 每日次数 | I1: 配置基础耗时秒 | J1: 开放星期 | K1: 进入消耗 | L1: 敌方门客数 | M1: 敌方护院总数 | N1: 掉落明细数 | O1: 固定项数 | P1: 概率项数 | Q1: 任务分类 | R1: 每周次数(帮会) | S1: 任务卡每日上限 | T1: 任务描述 | U1: 敌方统一科技等级 | V1: 敌方门客等级 | W1: 敌方门客属性加成 | X1: 固定奖励摘要 | Y1: 随机奖励摘要 | Z1: 显示排序配置 | AA1: 启用状态 | AB1: 推荐门客数(帮会) | AC1: 数据来源 | AD1: 进入消耗(JSON) | AE1: 敌方科技(JSON) | AF1: 原始任务配置(JSON) | AG1: 发起行动点消耗 | AH1: 奖励接收方
A2: 1 | B2: mid_autumn_moon_palace_trial | C2: 广寒宫试炼 | D2: 中级 | E2: task1 | F2: 否 | G2: 否 | H2: 3 | I2: 1800 | J2: 周二、周四、周六、周日 | K2: 无 | L2: =SUMIFS(敌方阵容!$F$2:$F$258,敌方阵容!$A$2:$A$258,B2,敌方阵容!$D$2:$D$258,"门客") -> 3 | M2: =SUMIFS(敌方阵容!$F$2:$F$258,敌方阵容!$A$2:$A$258,B2,敌方阵容!$D$2:$D$258,"护院") -> 800 | N2: =COUNTIF(任务掉落明细!$B$2:$B$66,B2) -> 2 | O2: =COUNTIFS(任务掉落明细!$B$2:$B$66,B2,任务掉落明细!$X$2:$X$66,1) -> 2 | P2: =COUNTIFS(任务掉落明细!$B$2:$B$66,B2,任务掉落明细!$X$2:$X$66,"<1") -> 0 | Q2: 个人任务 | S2: 5 | T2: 中秋将近，广寒宫外的月桂忽然枝叶疯长，遮蔽月华，连玉兔捣药的石臼也被散落的桂枝掩埋。吴刚日夜挥斧仍无法遏止异变，嫦娥只得向人间庄园主发出月宫请帖。 受邀者需穿过桂影迷阵，协助玉兔收集药材，并通过吴刚与嫦娥设下的月宫试炼。完成试炼者可带回月饼，也有机会获得三位月宫门客留下的召唤卷轴。 | U2: 7 | V2: 60 | W2: 0.12 | X2: 银两×40000；广寒宫试炼宝箱×1 | Y2: 开箱奖励及概率见宝箱奖励明细 | Z2: 1000 | AA2: 按配置导入 | AC2: data/mission_templates.yaml:mid_autumn_moon_palace_trial | AD2: {} | AE2: {"level":7,"guest_level":60,"guest_bonus":0.12} | AF2: {"key":"mid_autumn_moon_palace_trial","name":"广寒宫试炼","difficulty":"intermediate","available_weekdays":[2,4,6,7],"description":"中秋将近，广寒宫外的月桂忽然枝叶疯长，遮蔽月华，连玉兔捣药的石臼也被散落的桂枝掩埋。吴刚日夜挥斧仍无法遏止异变，嫦娥只得向人间庄园主发出月宫请帖。\n\n受邀者需穿过桂影迷阵，协助玉兔收集药材，并通过吴刚与嫦娥设下的月宫试炼。完成试炼者可带回月饼，也有机会获得三位月宫门客留下的召唤卷轴。\n","battle_type":"task1","base_travel_time":1800,"enemy_guests":[{"key":"myth_moon_jade_rabbit","label":"玉兔"},{"key":"myth_moon_wu_gang","label":"吴刚"},{"key":"hist_xianqin_0413","label":"嫦娥"}],"enemy_troops":{"quan_wang":300,"jian_hao":300,"divine_archer":200},"enemy_technology":{"level":7,"guest_level":60,"guest_bonus":0.12},"drop_table":{"silver":40000,"mission_chest_mid_autumn_moon_palace_trial":1},"daily_limit":3} | AG2: 10 | AH2: 挑战者庄园
A3: 2 | B3: kasukabe_daisakusen | C3: 春日部大作战 | D3: 中级 | E3: task1 | F3: 否 | G3: 否 | H3: 3 | I3: 1800 | J3: 周二、周四、周六、周日 | K3: 无 | L3: =SUMIFS(敌方阵容!$F$2:$F$258,敌方阵容!$A$2:$A$258,B3,敌方阵容!$D$2:$D$258,"门客") -> 5 | M3: =SUMIFS(敌方阵容!$F$2:$F$258,敌方阵容!$A$2:$A$258,B3,敌方阵容!$D$2:$D$258,"护院") -> 800 | N3: =COUNTIF(任务掉落明细!$B$2:$B$66,B3) -> 2 | O3: =COUNTIFS(任务掉落明细!$B$2:$B$66,B3,任务掉落明细!$X$2:$X$66,1) -> 2 | P3: =COUNTIFS(任务掉落明细!$B$2:$B$66,B3,任务掉落明细!$X$2:$X$66,"<1") -> 0 | Q3: 个人任务 | S3: 5 | T3: 庄园附近突然出现一支自称“春日部防卫队”的神秘队伍。他们本是追查被妖怪夺走的神奇蜡笔，却不慎把庄园周边画成了临时游乐战场：粮仓墙上长出大象鼻子，演武场地面变成蹦床，护院巡逻路线也被涂鸦迷宫搅得七零八落。 为了平息这场哭笑不得的混乱，庄主需要进入春日部游乐战场，突破玩具机关、恶作剧陷阱和防卫队试炼，击败被蜡笔力量影响的涂鸦大魔王，回收“小新的蜡笔”。集齐150个蜡笔后，可在仓库中招募紫色武门客「蜡笔小新」。 | U3: 7 | V3: 60 | W3: 0.12 | X3: 银两×40000；春日部大作战宝箱×1 | Y3: 开箱奖励及概率见宝箱奖励明细 | Z3: 1000 | AA3: 按配置导入 | AC3: data/mission_templates.yaml:kasukabe_daisakusen | AD3: {} | AE3: {"level":7,"guest_level":60,"guest_bonus":0.12} | AF3: {"key":"kasukabe_daisakusen","name":"春日部大作战","difficulty":"intermediate","available_weekdays":[2,4,6,7],"description":"庄园附近突然出现一支自称“春日部防卫队”的神秘队伍。他们本是追查被妖怪夺走的神奇蜡笔，却不慎把庄园周边画成了临时游乐战场：粮仓墙上长出大象鼻子，演武场地面变成蹦床，护院巡逻路线也被涂鸦迷宫搅得七零八落。\n\n为了平息这场哭笑不得的混乱，庄主需要进入春日部游乐战场，突破玩具机关、恶作剧陷阱和防卫队试炼，击败被蜡笔力量影响的涂鸦大魔王，回收“小新的蜡笔”。集齐150个蜡笔后，可在仓库中招募紫色武门客「蜡笔小新」。\n","battle_type":"task1","enemy_guests":[{"key":"task_kasukabe_patrol_captain","label":"春日部巡逻队长"},{"key":"task_kasukabe_toy_crocodile","label":"玩具机关鳄鱼"},{"key":"task_kasukabe_defense_member","label":"迷路的防卫队员"},{"key":"task_kasukabe_crayon_clone","label":"蜡笔恶作剧分身"},{"key":"task_kasukabe_doodle_boss","label":"涂鸦大魔王"}],"enemy_troops":{"quan_wang":300,"archer":300,"dao_ba":200},"enemy_technology":{"level":7,"guest_level":60,"guest_bonus":0.12},"drop_table":{"silver":40000,"mission_chest_kasukabe_daisakusen":1},"daily_limit":3} | AG3: 10 | AH3: 挑战者庄园
A4: 3 | B4: huashan_lunjian | C4: 华山论贱 | D4: 初级 | E4: task1 | F4: 否 | G4: 是 | H4: 3 | I4: 1800 | J4: 每日开放 | K4: 无 | L4: =SUMIFS(敌方阵容!$F$2:$F$258,敌方阵容!$A$2:$A$258,B4,敌方阵容!$D$2:$D$258,"门客") -> 4 | M4: =SUMIFS(敌方阵容!$F$2:$F$258,敌方阵容!$A$2:$A$258,B4,敌方阵容!$D$2:$D$258,"护院") -> 0 | N4: =COUNTIF(任务掉落明细!$B$2:$B$66,B4) -> 2 | O4: =COUNTIFS(任务掉落明细!$B$2:$B$66,B4,任务掉落明细!$X$2:$X$66,1) -> 2 | P4: =COUNTIFS(任务掉落明细!$B$2:$B$66,B4,任务掉落明细!$X$2:$X$66,"<1") -> 0 | Q4: 个人任务 | S4: 5 | T4: 中原大地，经过无数年的风吹雨打，各大贱派均元气大伤，数百年的休养调整使各大贱客高手知耻后勇，不断创新各种贱术秘籍，停办经年的贱客比武大赛将顺应民意在华山之巅重新开启，各路英雄贱客可在此大展身手，争当新一届人见人爱、花见花开的贱客之王，在此和谐社会留下自己奋斗的印记。 | U4: 2 | V4: 12 | W4: 0 | X4: 银两×8000；华山论贱宝箱×1 | Y4: 开箱奖励及概率见宝箱奖励明细 | Z4: 2 | AA4: 按配置导入 | AC4: data/mission_templates.yaml:huashan_lunjian | AD4: {} | AE4: {"level":2,"guest_level":12,"guest_bonus":0} | AF4: {"key":"huashan_lunjian","name":"华山论贱","display_order":2,"difficulty":"junior","description":"中原大地，经过无数年的风吹雨打，各大贱派均元气大伤，数百年的休养调整使各大贱客高手知耻后勇，不断创新各种贱术秘籍，停办经年的贱客比武大赛将顺应民意在华山之巅重新开启，各路英雄贱客可在此大展身手，争当新一届人见人爱、花见花开的贱客之王，在此和谐社会留下自己奋斗的印记。\n","battle_type":"task1","guest_only":true,"enemy_guests":[{"key":"task_huashan_jianwang","label":"贱王之王"},{"key":"task_huashan_jianjing","label":"顶级贱精"},{"key":"task_huashan_jianjing","label":"顶级贱精"},{"key":"task_huashan_audience_a","label":"观众甲"}],"enemy_technology":{"level":2,"guest_level":12,"guest_bonus":0},"drop_table":{"silver":8000,"mission_chest_huashan_lunjian":1},"daily_limit":3} | AG4: 10 | AH4: 挑战者庄园
A5: 4 | B5: wagangzhai_nixi | C5: 瓦岗寨的逆袭 | D5: 中级 | E5: task1 | F5: 是 | G5: 否 | H5: 3 | I5: 1800 | J5: 每日开放 | K5: 无 | L5: =SUMIFS(敌方阵容!$F$2:$F$258,敌方阵容!$A$2:$A$258,B5,敌方阵容!$D$2:$D$258,"门客") -> 6 | M5: =SUMIFS(敌方阵容!$F$2:$F$258,敌方阵容!$A$2:$A$258,B5,敌方阵容!$D$2:$D$258,"护院") -> 2400 | N5: =COUNTIF(任务掉落明细!$B$2:$B$66,B5) -> 2 | O5: =COUNTIFS(任务掉落明细!$B$2:$B$66,B5,任务掉落明细!$X$2:$X$66,1) -> 2 | P5: =COUNTIFS(任务掉落明细!$B$2:$B$66,B5,任务掉落明细!$X$2:$X$66,"<1") -> 0 | Q5: 个人任务 | S5: 5 | T5: 在上一次广大庄园主联手扫荡瓦岗寨时，正值瓦岗五虎出门执行任务，翟让和程咬金输的并不服气，为了证明瓦岗寨的实力，翟让率领瓦岗五虎"秦叔宝"、"单雄信"、"王伯当"、"罗成"、"程咬金"携山寨喽啰兵600人亲自上各庄园寻衅……这一次的战场变成了您的庄园，请加强防御设施，让您的门客和护院准备好迎接战斗洗礼。 | U5: 10 | V5: 100 | W5: 0.3 | X5: 银两×40000；瓦岗寨的逆袭宝箱×1 | Y5: 开箱奖励及概率见宝箱奖励明细 | Z5: 7 | AA5: 按配置导入 | AC5: data/mission_templates.yaml:wagangzhai_nixi | AD5: {} | AE5: {"level":10,"guest_level":100,"guest_bonus":0.3} | AF5: {"key":"wagangzhai_nixi","name":"瓦岗寨的逆袭","difficulty":"intermediate","description":"在上一次广大庄园主联手扫荡瓦岗寨时，正值瓦岗五虎出门执行任务，翟让和程咬金输的并不服气，为了证明瓦岗寨的实力，翟让率领瓦岗五虎\"秦叔宝\"、\"单雄信\"、\"王伯当\"、\"罗成\"、\"程咬金\"携山寨喽啰兵600人亲自上各庄园寻衅……这一次的战场变成了您的庄园，请加强防御设施，让您的门客和护院准备好迎接战斗洗礼。\n","battle_type":"task1","is_defense":true,"display_order":7,"enemy_guests":[{"key":"hist_suitang_0162_zhairang","skills":["tangseng_sermon"]},{"key":"hero_qin_shubao","skills":["brahma_true_fire"]},"hist_suitang_0164_shanxiongxin","hist_suitang_0165_wangbodang","hero_luo_cheng","hero_cheng_yaojin"],"enemy_technology":{"level":10,"guest_level":100,"guest_bonus":0.3},"enemy_troops":{"arrow_god":800,"quan_sheng":800,"qiang_wang":800},"drop_table":{"silver":40000,"mission_chest_wagangzhai_nixi":1},"base_travel_time":1800,"daily_limit":3} | AG5: 10 | AH5: 挑战者庄园
A6: 5 | B6: jingyanggang | C6: 景阳冈 | D6: 初级 | E6: task1 | F6: 否 | G6: 是 | H6: 3 | I6: 1800 | J6: 每日开放 | K6: 无 | L6: =SUMIFS(敌方阵容!$F$2:$F$258,敌方阵容!$A$2:$A$258,B6,敌方阵容!$D$2:$D$258,"门客") -> 1 | M6: =SUMIFS(敌方阵容!$F$2:$F$258,敌方阵容!$A$2:$A$258,B6,敌方阵容!$D$2:$D$258,"护院") -> 0 | N6: =COUNTIF(任务掉落明细!$B$2:$B$66,B6) -> 2 | O6: =COUNTIFS(任务掉落明细!$B$2:$B$66,B6,任务掉落明细!$X$2:$X$66,1) -> 2 | P6: =COUNTIFS(任务掉落明细!$B$2:$B$66,B6,任务掉落明细!$X$2:$X$66,"<1") -> 0 | Q6: 个人任务 | S6: 5 | T6: 景阳冈上有只吊睛白额大虫伤害人命，官府多次派猎户擒捉未果，往客商人只能在巳午未三个时辰结伴过冈，其馀时分，及单身客人，不能过冈，恐被伤害性命。 | U6: 3 | V6: 15 | W6: 0.02 | X6: 银两×7000；景阳冈宝箱×1 | Y6: 开箱奖励及概率见宝箱奖励明细 | Z6: 1 | AA6: 按配置导入 | AC6: data/mission_templates.yaml:jingyanggang | AD6: {} | AE6: {"level":3,"guest_level":15,"guest_bonus":0.02} | AF6: {"key":"jingyanggang","name":"景阳冈","display_order":1,"difficulty":"junior","description":"景阳冈上有只吊睛白额大虫伤害人命，官府多次派猎户擒捉未果，往客商人只能在巳午未三个时辰结伴过冈，其馀时分，及单身客人，不能过冈，恐被伤害性命。\n","battle_type":"task1","guest_only":true,"enemy_guests":[{"key":"task_jingyang_tiger","label":"猛虎"}],"enemy_technology":{"level":3,"guest_level":15,"guest_bonus":0.02},"drop_table":{"silver":7000,"mission_chest_jingyanggang":1},"daily_limit":3} | AG6: 10 | AH6: 挑战者庄园
A7: 6 | B7: wulongshan | C7: 乌龙山 | D7: 初级 | E7: task1 | F7: 否 | G7: 否 | H7: 3 | I7: 1800 | J7: 每日开放 | K7: 无 | L7: =SUMIFS(敌方阵容!$F$2:$F$258,敌方阵容!$A$2:$A$258,B7,敌方阵容!$D$2:$D$258,"门客") -> 2 | M7: =SUMIFS(敌方阵容!$F$2:$F$258,敌方阵容!$A$2:$A$258,B7,敌方阵容!$D$2:$D$258,"护院") -> 200 | N7: =COUNTIF(任务掉落明细!$B$2:$B$66,B7) -> 2 | O7: =COUNTIFS(任务掉落明细!$B$2:$B$66,B7,任务掉落明细!$X$2:$X$66,1) -> 2 | P7: =COUNTIFS(任务掉落明细!$B$2:$B$66,B7,任务掉落明细!$X$2:$X$66,"<1") -> 0 | Q7: 个人任务 | S7: 5 | T7: 湘黔边界的乌龙山鲜少人迹，这里盘聚着一帮强盗将那里作为他们的大本营。他们借这乱世之际四处行凶，烧杀凌掠无恶不作，种种罪行令人发指。由于此帮强盗行迹过于放肆导致朝野上下为之震动，朝廷号召各方能人尽快歼灭这帮流寇。 | U7: 4 | V7: 20 | W7: 0.04 | X7: 银两×15000；乌龙山宝箱×1 | Y7: 开箱奖励及概率见宝箱奖励明细 | Z7: 4 | AA7: 按配置导入 | AC7: data/mission_templates.yaml:wulongshan | AD7: {} | AE7: {"level":4,"guest_level":20,"guest_bonus":0.04} | AF7: {"key":"wulongshan","name":"乌龙山","difficulty":"junior","display_order":4,"description":"湘黔边界的乌龙山鲜少人迹，这里盘聚着一帮强盗将那里作为他们的大本营。他们借这乱世之际四处行凶，烧杀凌掠无恶不作，种种罪行令人发指。由于此帮强盗行迹过于放肆导致朝野上下为之震动，朝廷号召各方能人尽快歼灭这帮流寇。\n","battle_type":"task1","enemy_guests":[{"key":"task_wulong_bandit_chief_zuanshanbao","label":"钻山豹"},{"key":"task_wulong_bandit_chief_zuoshandiao","label":"座山雕"}],"enemy_technology":{"level":4,"guest_level":20,"guest_bonus":0.04},"enemy_troops":{"qiang_ke":200},"drop_table":{"silver":15000,"mission_chest_wulongshan":1},"daily_limit":3} | AG7: 10 | AH7: 挑战者庄园
A8: 7 | B8: wagangzhai | C8: 瓦岗寨 | D8: 初级 | E8: task1 | F8: 否 | G8: 否 | H8: 3 | I8: 1800 | J8: 每日开放 | K8: 无 | L8: =SUMIFS(敌方阵容!$F$2:$F$258,敌方阵容!$A$2:$A$258,B8,敌方阵容!$D$2:$D$258,"门客") -> 2 | M8: =SUMIFS(敌方阵容!$F$2:$F$258,敌方阵容!$A$2:$A$258,B8,敌方阵容!$D$2:$D$258,"护院") -> 400 | N8: =COUNTIF(任务掉落明细!$B$2:$B$66,B8) -> 2 | O8: =COUNTIFS(任务掉落明细!$B$2:$B$66,B8,任务掉落明细!$X$2:$X$66,1) -> 2 | P8: =COUNTIFS(任务掉落明细!$B$2:$B$66,B8,任务掉落明细!$X$2:$X$66,"<1") -> 0 | Q8: 个人任务 | S8: 5 | T8: 瓦岗寨原来的寨主翟让被程咬金击败后让出寨主之位，程咬金自号"大魔国混世魔王"，并带领瓦岗军四处出门踢馆打劫，引得各地庄园主怨声在道，大家决定联手打击瓦岗寨，维护和保障各庄园的和平与稳定。 | U8: 5 | V8: 35 | W8: 0.1 | X8: 银两×20000；瓦岗寨宝箱×1 | Y8: 开箱奖励及概率见宝箱奖励明细 | Z8: 5 | AA8: 按配置导入 | AC8: data/mission_templates.yaml:wagangzhai | AD8: {} | AE8: {"level":5,"guest_level":35,"guest_bonus":0.1} | AF8: {"key":"wagangzhai","name":"瓦岗寨","difficulty":"junior","display_order":5,"description":"瓦岗寨原来的寨主翟让被程咬金击败后让出寨主之位，程咬金自号\"大魔国混世魔王\"，并带领瓦岗军四处出门踢馆打劫，引得各地庄园主怨声在道，大家决定联手打击瓦岗寨，维护和保障各庄园的和平与稳定。\n","battle_type":"task1","enemy_guests":["hero_cheng_yaojin","hist_suitang_0162_zhairang"],"enemy_troops":{"jian_xia":400},"enemy_technology":{"level":5,"guest_level":35,"guest_bonus":0.1},"drop_table":{"silver":20000,"mission_chest_wagangzhai":1},"daily_limit":3} | AG8: 10 | AH8: 挑战者庄园
A9: 8 | B9: fugui_shanzhuang | C9: 富贵山庄 | D9: 初级 | E9: task1 | F9: 否 | G9: 是 | H9: 3 | I9: 1800 | J9: 每日开放 | K9: 无 | L9: =SUMIFS(敌方阵容!$F$2:$F$258,敌方阵容!$A$2:$A$258,B9,敌方阵容!$D$2:$D$258,"门客") -> 1 | M9: =SUMIFS(敌方阵容!$F$2:$F$258,敌方阵容!$A$2:$A$258,B9,敌方阵容!$D$2:$D$258,"护院") -> 0 | N9: =COUNTIF(任务掉落明细!$B$2:$B$66,B9) -> 2 | O9: =COUNTIFS(任务掉落明细!$B$2:$B$66,B9,任务掉落明细!$X$2:$X$66,1) -> 2 | P9: =COUNTIFS(任务掉落明细!$B$2:$B$66,B9,任务掉落明细!$X$2:$X$66,"<1") -> 0 | Q9: 个人任务 | S9: 5 | T9: 富贵山庄，其美甲天下、其富可敌国，庄主张富贵更是好客之人，但凡江湖有难，他都不遗余力伸出援助之手，解人燃眉。故被人予以"雪中炭"之美名。江湖多有时运不济、怀才不遇的落魄之士，若想求得张庄主帮助，必先证明自己才识。在接受庄主考验后，若能得到庄主赏识，则日后必荣禄相授。 | U9: 3 | V9: 40 | W9: 0.05 | X9: 银两×14000；富贵山庄宝箱×1 | Y9: 开箱奖励及概率见宝箱奖励明细 | Z9: 3 | AA9: 按配置导入 | AC9: data/mission_templates.yaml:fugui_shanzhuang | AD9: {} | AE9: {"level":3,"guest_level":40,"guest_bonus":0.05} | AF9: {"key":"fugui_shanzhuang","name":"富贵山庄","difficulty":"junior","display_order":3,"description":"富贵山庄，其美甲天下、其富可敌国，庄主张富贵更是好客之人，但凡江湖有难，他都不遗余力伸出援助之手，解人燃眉。故被人予以\"雪中炭\"之美名。江湖多有时运不济、怀才不遇的落魄之士，若想求得张庄主帮助，必先证明自己才识。在接受庄主考验后，若能得到庄主赏识，则日后必荣禄相授。\n","battle_type":"task1","guest_only":true,"enemy_guests":[{"key":"task_fugui_instructor","label":"武师教头"}],"enemy_technology":{"level":3,"guest_level":40,"guest_bonus":0.05},"drop_table":{"silver":14000,"mission_chest_fugui_shanzhuang":1},"daily_limit":3} | AG9: 10 | AH9: 挑战者庄园
A10: 9 | B10: shizipo_heidian | C10: 十字坡黑店 | D10: 中级 | E10: task1 | F10: 否 | G10: 否 | H10: 3 | I10: 1800 | J10: 每日开放 | K10: 无 | L10: =SUMIFS(敌方阵容!$F$2:$F$258,敌方阵容!$A$2:$A$258,B10,敌方阵容!$D$2:$D$258,"门客") -> 2 | M10: =SUMIFS(敌方阵容!$F$2:$F$258,敌方阵容!$A$2:$A$258,B10,敌方阵容!$D$2:$D$258,"护院") -> 700 | N10: =COUNTIF(任务掉落明细!$B$2:$B$66,B10) -> 2 | O10: =COUNTIFS(任务掉落明细!$B$2:$B$66,B10,任务掉落明细!$X$2:$X$66,1) -> 2 | P10: =COUNTIFS(任务掉落明细!$B$2:$B$66,B10,任务掉落明细!$X$2:$X$66,"<1") -> 0 | Q10: 个人任务 | S10: 5 | T10: 孙二娘和张青在十字坡开酒店，常用蒙汗药蒙翻过往行人。他们将行人杀死后，大块好肉当作黄牛肉卖，零碎小肉，做馅包馒头。江湖有传言说："大树十字坡，客人谁敢那里过？肥的切做馒头馅，瘦的却丢去填河。" | U10: 6 | V10: 70 | W10: 0.1 | X10: 银两×30000；十字坡黑店宝箱×1 | Y10: 开箱奖励及概率见宝箱奖励明细 | Z10: 5 | AA10: 按配置导入 | AC10: data/mission_templates.yaml:shizipo_heidian | AD10: {} | AE10: {"level":6,"guest_level":70,"guest_bonus":0.1} | AF10: {"key":"shizipo_heidian","name":"十字坡黑店","difficulty":"intermediate","display_order":5,"description":"孙二娘和张青在十字坡开酒店，常用蒙汗药蒙翻过往行人。他们将行人杀死后，大块好肉当作黄牛肉卖，零碎小肉，做馅包馒头。江湖有传言说：\"大树十字坡，客人谁敢那里过？肥的切做馒头馅，瘦的却丢去填河。\"\n","battle_type":"task1","enemy_guests":[{"key":"task_shizipo_sun_erniang","label":"孙二娘"},{"key":"task_shizipo_zhang_qing","label":"张青"}],"enemy_troops":{"quan_wang":300,"divine_archer":300,"dao_ba":100},"enemy_technology":{"level":6,"guest_level":70,"guest_bonus":0.1},"drop_table":{"silver":30000,"mission_chest_shizipo_heidian":1},"daily_limit":3} | AG10: 10 | AH10: 挑战者庄园
A11: 10 | B11: shanhaiguan | C11: 山海关 | D11: 中级 | E11: task1 | F11: 否 | G11: 否 | H11: 3 | I11: 1800 | J11: 每日开放 | K11: 无 | L11: =SUMIFS(敌方阵容!$F$2:$F$258,敌方阵容!$A$2:$A$258,B11,敌方阵容!$D$2:$D$258,"门客") -> 2 | M11: =SUMIFS(敌方阵容!$F$2:$F$258,敌方阵容!$A$2:$A$258,B11,敌方阵容!$D$2:$D$258,"护院") -> 1500 | N11: =COUNTIF(任务掉落明细!$B$2:$B$66,B11) -> 2 | O11: =COUNTIFS(任务掉落明细!$B$2:$B$66,B11,任务掉落明细!$X$2:$X$66,1) -> 2 | P11: =COUNTIFS(任务掉落明细!$B$2:$B$66,B11,任务掉落明细!$X$2:$X$66,"<1") -> 0 | Q11: 个人任务 | S11: 5 | T11: 山海关所在的河西走廊是华北通向东北的咽喉地带，是一座及其重要的军事重镇，主要防御外族势力的入侵。吴三桂作为镇守山海关的大将，居然意图勾结外族势力，入侵中原。 | U11: 7 | V11: 70 | W11: 0.18 | X11: 银两×40000；山海关宝箱×1 | Y11: 开箱奖励及概率见宝箱奖励明细 | Z11: 6 | AA11: 按配置导入 | AC11: data/mission_templates.yaml:shanhaiguan | AD11: {} | AE11: {"level":7,"guest_level":70,"guest_bonus":0.18} | AF11: {"key":"shanhaiguan","name":"山海关","difficulty":"intermediate","display_order":6,"description":"山海关所在的河西走廊是华北通向东北的咽喉地带，是一座及其重要的军事重镇，主要防御外族势力的入侵。吴三桂作为镇守山海关的大将，居然意图勾结外族势力，入侵中原。\n","battle_type":"task1","enemy_guests":["hist_mingqing_0230","hist_mingqing_0054"],"enemy_troops":{"jian_sheng":500,"quan_wang":500,"qiang_ba":500},"enemy_technology":{"level":7,"guest_level":70,"guest_bonus":0.18},"drop_table":{"silver":40000,"mission_chest_shanhaiguan":1},"daily_limit":3} | AG11: 10 | AH11: 挑战者庄园
A12: 11 | B12: shiren_daochang | C12: 十人道场 | D12: 中级 | E12: task1 | F12: 否 | G12: 否 | H12: 3 | I12: 1800 | J12: 每日开放 | K12: 无 | L12: =SUMIFS(敌方阵容!$F$2:$F$258,敌方阵容!$A$2:$A$258,B12,敌方阵容!$D$2:$D$258,"门客") -> 10 | M12: =SUMIFS(敌方阵容!$F$2:$F$258,敌方阵容!$A$2:$A$258,B12,敌方阵容!$D$2:$D$258,"护院") -> 0 | N12: =COUNTIF(任务掉落明细!$B$2:$B$66,B12) -> 2 | O12: =COUNTIFS(任务掉落明细!$B$2:$B$66,B12,任务掉落明细!$X$2:$X$66,1) -> 2 | P12: =COUNTIFS(任务掉落明细!$B$2:$B$66,B12,任务掉落明细!$X$2:$X$66,"<1") -> 0 | Q12: 个人任务 | S12: 5 | T12: 十人道场是春秋世界初级试炼之地，由恶人谷十大恶人驻守。只要能击败十大恶人，通过试炼，就能极速提升门客的等级和能力。 | U12: 6 | V12: 55 | W12: 0.08 | X12: 银两×20000；十人道场宝箱×1 | Y12: 开箱奖励及概率见宝箱奖励明细 | Z12: 3 | AA12: 按配置导入 | AC12: data/mission_templates.yaml:shiren_daochang | AD12: {} | AE12: {"level":6,"guest_level":55,"guest_bonus":0.08} | AF12: {"key":"shiren_daochang","name":"十人道场","difficulty":"intermediate","display_order":3,"description":"十人道场是春秋世界初级试炼之地，由恶人谷十大恶人驻守。只要能击败十大恶人，通过试炼，就能极速提升门客的等级和能力。\n","battle_type":"task1","enemy_guests":["hero_du_sha","hero_li_dazui","hero_hahaer","hero_tu_jiaojiao","hero_yin_jiuyou",{"key":"task_shiren_xiaomimi","label":"萧咪咪"},{"key":"task_shiren_xuanyuansanguang","label":"轩辕三光"},{"key":"task_shiren_tiezhan","label":"铁战"},"hero_bai_kaixin",{"key":"task_shiren_luoshixiongdi","label":"罗氏兄弟"}],"enemy_technology":{"level":6,"guest_level":55,"guest_bonus":0.08},"drop_table":{"silver":20000,"mission_chest_shiren_daochang":1},"daily_limit":3} | AG12: 10 | AH12: 挑战者庄园
A13: 12 | B13: jiguanshou_chuxian | C13: 机关兽初现 | D13: 初级 | E13: task1 | F13: 否 | G13: 否 | H13: 2 | I13: 1800 | J13: 每日开放 | K13: 无 | L13: =SUMIFS(敌方阵容!$F$2:$F$258,敌方阵容!$A$2:$A$258,B13,敌方阵容!$D$2:$D$258,"门客") -> 8 | M13: =SUMIFS(敌方阵容!$F$2:$F$258,敌方阵容!$A$2:$A$258,B13,敌方阵容!$D$2:$D$258,"护院") -> 0 | N13: =COUNTIF(任务掉落明细!$B$2:$B$66,B13) -> 2 | O13: =COUNTIFS(任务掉落明细!$B$2:$B$66,B13,任务掉落明细!$X$2:$X$66,1) -> 2 | P13: =COUNTIFS(任务掉落明细!$B$2:$B$66,B13,任务掉落明细!$X$2:$X$66,"<1") -> 0 | Q13: 个人任务 | S13: 1 | T13: 乔家村以制做灵活轻巧、栩栩如生的「机械猫」闻名于天下。「机械猫」又称之为「钟离猫」，相传是墨家子弟孙钟离路过此地时，时逢村中鼠患肆虐，为清除鼠患取当地木材仿猫型制成。经历代乔家村民不断改良，「机械猫」以生具灵性、精巧无比，并作用于生活各用途中。某日乔家村第一铁匠乔大牛家中被盗，八只刚制成的「机械猫」见房门未锁，逃离乔家村。随后，逃离的八只「机械猫」开始在乔家村附近肆虐作恶，搞得乔家村民苦不堪言。 | U13: 7 | V13: 35 | W13: 0.12 | X13: 银两×24000；机关兽初现宝箱×1 | Y13: 开箱奖励及概率见宝箱奖励明细 | Z13: 7 | AA13: 按配置导入 | AC13: data/mission_templates.yaml:jiguanshou_chuxian | AD13: {} | AE13: {"level":7,"guest_level":35,"guest_bonus":0.12} | AF13: {"key":"jiguanshou_chuxian","name":"机关兽初现","difficulty":"junior","display_order":7,"description":"乔家村以制做灵活轻巧、栩栩如生的「机械猫」闻名于天下。「机械猫」又称之为「钟离猫」，相传是墨家子弟孙钟离路过此地时，时逢村中鼠患肆虐，为清除鼠患取当地木材仿猫型制成。经历代乔家村民不断改良，「机械猫」以生具灵性、精巧无比，并作用于生活各用途中。某日乔家村第一铁匠乔大牛家中被盗，八只刚制成的「机械猫」见房门未锁，逃离乔家村。随后，逃离的八只「机械猫」开始在乔家村附近肆虐作恶，搞得乔家村民苦不堪言。\n","battle_type":"task1","enemy_guests":[{"key":"task_mechanism_cat","label":"改装机械猫"},{"key":"task_mechanism_cat","label":"改装机械猫"},{"key":"task_mechanism_cat","label":"改装机械猫"},{"key":"task_mechanism_cat","label":"改装机械猫"},{"key":"task_mechanism_cat","label":"改装机械猫"},{"key":"task_mechanism_cat","label":"改装机械猫"},{"key":"task_mechanism_cat","label":"改装机械猫"},{"key":"task_mechanism_cat","label":"改装机械猫"}],"enemy_technology":{"level":7,"guest_level":35,"guest_bonus":0.12},"drop_table":{"silver":24000,"mission_chest_jiguanshou_chuxian":1},"daily_limit":2,"mission_card_daily_limit":1} | AG13: 10 | AH13: 挑战者庄园
... A33: 32 | B33: baimenlou_mingyun_jueze | C33: 飞将浮沉录：白门楼命运抉择 | D33: 高级 | E33: task1 | F33: 否 | G33: 否 | H33: 1 | I33: 2700 | J33: 每日开放 | K33: 虎牢关战旗×1 | L33: =SUMIFS(敌方阵容!$F$2:$F$258,敌方阵容!$A$2:$A$258,B33,敌方阵容!$D$2:$D$258,"门客") -> 5 | M33: =SUMIFS(敌方阵容!$F$2:$F$258,敌方阵容!$A$2:$A$258,B33,敌方阵容!$D$2:$D$258,"护院") -> 7800 | N33: =COUNTIF(任务掉落明细!$B$2:$B$66,B33) -> 2 | O33: =COUNTIFS(任务掉落明细!$B$2:$B$66,B33,任务掉落明细!$X$2:$X$66,1) -> 2 | P33: =COUNTIFS(任务掉落明细!$B$2:$B$66,B33,任务掉落明细!$X$2:$X$66,"<1") -> 0 | Q33: 个人任务 | S33: 5 | T33: 虎牢关战旗染血之后，曹军围住下邳，白门楼成了吕布最后的落脚处。高顺在整军，张辽在寻找退路，陈宫在推演一条不必投降的路，臧霸守着最后的旧部；而吕布仍相信，只要再给他一次冲阵的机会，天下就还没有真正决定谁会输。 然而江湖传闻，白门楼风声最紧时，总有一张没有落款的招贤帖在暗中流转。若它最终落到有缘人手中，史书上那句“吕布死于白门楼”未必还能照抄，城楼之下或许会多出一位改旗易帜的绝世猛将；只是新东家能不能压住他的脾气，就要看庄园主自己的本事了。 进入此关需要消耗一面「虎牢关战旗」。庄园主须击破吕布、高顺、张辽、陈宫与臧霸的合围，替这段乱世故事写下最后一笔。 | U33: 10 | V33: 100 | W33: 0.8 | X33: 银两×180000；白门楼宝箱×1 | Y33: 开箱奖励及概率见宝箱奖励明细 | Z33: 1003 | AA33: 按配置导入 | AC33: data/mission_templates.yaml:baimenlou_mingyun_jueze | AD33: {"hulao_war_banner":1} | AE33: {"level":10,"guest_level":100,"guest_bonus":0.8} | AF33: {"key":"baimenlou_mingyun_jueze","name":"飞将浮沉录：白门楼命运抉择","display_order":1003,"difficulty":"advanced","description":"虎牢关战旗染血之后，曹军围住下邳，白门楼成了吕布最后的落脚处。高顺在整军，张辽在寻找退路，陈宫在推演一条不必投降的路，臧霸守着最后的旧部；而吕布仍相信，只要再给他一次冲阵的机会，天下就还没有真正决定谁会输。\n\n然而江湖传闻，白门楼风声最紧时，总有一张没有落款的招贤帖在暗中流转。若它最终落到有缘人手中，史书上那句“吕布死于白门楼”未必还能照抄，城楼之下或许会多出一位改旗易帜的绝世猛将；只是新东家能不能压住他的脾气，就要看庄园主自己的本事了。\n\n进入此关需要消耗一面「虎牢关战旗」。庄园主须击破吕布、高顺、张辽、陈宫与臧霸的合围，替这段乱世故事写下最后一笔。\n","battle_type":"task1","entry_cost":{"hulao_war_banner":1},"enemy_guests":[{"key":"task_baimenlou_lvbu","label":"吕布"},{"key":"task_baimenlou_gaoshun","label":"高顺"},{"key":"task_baimenlou_zhangliao","label":"张辽"},{"key":"task_baimenlou_chengong","label":"陈宫"},{"key":"task_baimenlou_zangba","label":"臧霸"}],"enemy_troops":{"dao_sheng":1800,"qiang_wang":1700,"jian_sheng":1600,"quan_sheng":1200,"arrow_god":1500},"enemy_technology":{"level":10,"guest_level":100,"guest_bonus":0.8},"drop_table":{"silver":180000,"mission_chest_baimenlou_mingyun_jueze":1},"base_travel_time":2700,"daily_limit":1} | AG33: 10 | AH33: 挑战者庄园
A34: 33 | B34: guild_patrol_alpha | C34: 夜袭乌鳞寨 | D34: 初级 | E34: troop | F34: 否 | G34: 否 | I34: 1500 | J34: 每日开放 | K34: 无 | L34: =SUMIFS(敌方阵容!$F$2:$F$258,敌方阵容!$A$2:$A$258,B34,敌方阵容!$D$2:$D$258,"门客") -> 12 | M34: =SUMIFS(敌方阵容!$F$2:$F$258,敌方阵容!$A$2:$A$258,B34,敌方阵容!$D$2:$D$258,"护院") -> 2610 | N34: =COUNTIF(任务掉落明细!$B$2:$B$66,B34) -> 1 | O34: =COUNTIFS(任务掉落明细!$B$2:$B$66,B34,任务掉落明细!$X$2:$X$66,1) -> 1 | P34: =COUNTIFS(任务掉落明细!$B$2:$B$66,B34,任务掉落明细!$X$2:$X$66,"<1") -> 0 | Q34: 帮会任务 | R34: 3 | T34: 近来北郊商道一入子夜便灯火尽灭，往返车队不是失了骡马，便是天明后只剩翻倒车辙。帮中弟子顺着断箭、碎缰和半截焦木一路摸到山坳，才看见乌鳞寨早把谷口修成了连环哨卡，拒马、暗哨与巡夜火把一层压着一层。 寨中人白日敛迹，夜里却轮番下山掠货，惯会先放小股人手引人追击，再借山路弯口突然合围。若想把这条商线重新打通，不能只顾着往前压，还得有人盯住两翼伏兵，免得主力刚进谷口，退路便先被人摸黑截断。 | U34: 7 | V34: 88 | W34: 0.36 | X34: 红宝石×96（帮会仓库） | Y34: 无 | Z34: 10 | AA34: 是 | AB34: 10 | AC34: data/guild_mission_templates.yaml:L9 | AD34: {} | AE34: {"level":7,"guest_level":88,"guest_bonus":0.36} | AF34: {"key":"guild_patrol_alpha","name":"夜袭乌鳞寨","description":"近来北郊商道一入子夜便灯火尽灭，往返车队不是失了骡马，便是天明后只剩翻倒车辙。帮中弟子顺着断箭、碎缰和半截焦木一路摸到山坳，才看见乌鳞寨早把谷口修成了连环哨卡，拒马、暗哨与巡夜火把一层压着一层。\n\n寨中人白日敛迹，夜里却轮番下山掠货，惯会先放小股人手引人追击，再借山路弯口突然合围。若想把这条商线重新打通，不能只顾着往前压，还得有人盯住两翼伏兵，免得主力刚进谷口，退路便先被人摸黑截断。\n","difficulty":"junior","task_type":"troop","base_duration_seconds":1500,"ruby_reward":96,"weekly_limit":3,"recommended_guest_count":10,"allow_troops":true,"enemy_guests":[{"template_key":"guild_wulinzhai_zhai_zhu"},{"template_key":"guild_wulinzhai_junshi"},{"template_key":"guild_wulinzhai_night_watch"},{"template_key":"guild_wulinzhai_blade_ambusher"},{"template_key":"guild_wulinzhai_blade_ambusher"},{"template_key":"guild_wulinzhai_blade_ambusher"},{"template_key":"guild_wulinzhai_torch_archer"},{"template_key":"guild_wulinzhai_torch_archer"},{"template_key":"guild_wulinzhai_torch_archer"},{"template_key":"guild_wulinzhai_path_scout"},{"template_key":"guild_wulinzhai_minion"},{"template_key":"guild_wulinzhai_minion"}],"enemy_troops":{"qiang_hao":760,"jian_hao":700,"fast_archer":650,"dao_jie":500},"enemy_technology":{"level":7,"guest_level":88,"guest_bonus":0.36},"is_active":true,"sort_weight":10} | AH34: 帮会仓库
A35: 34 | B35: guild_supply_escort | C35: 血旗镖局风云 | D35: 中级 | E35: troop | F35: 否 | G35: 否 | I35: 2100 | J35: 每日开放 | K35: 无 | L35: =SUMIFS(敌方阵容!$F$2:$F$258,敌方阵容!$A$2:$A$258,B35,敌方阵容!$D$2:$D$258,"门客") -> 16 | M35: =SUMIFS(敌方阵容!$F$2:$F$258,敌方阵容!$A$2:$A$258,B35,敌方阵容!$D$2:$D$258,"护院") -> 4100 | N35: =COUNTIF(任务掉落明细!$B$2:$B$66,B35) -> 1 | O35: =COUNTIFS(任务掉落明细!$B$2:$B$66,B35,任务掉落明细!$X$2:$X$66,1) -> 1 | P35: =COUNTIFS(任务掉落明细!$B$2:$B$66,B35,任务掉落明细!$X$2:$X$66,"<1") -> 0 | Q35: 帮会任务 | R35: 3 | T35: 血旗镖局表面替各路商号押送金银药材，暗地里却替人收账、截货、买命，沿河几个渡口最近都挂上了他们的旗。凡是不肯交路银的商队，不是半夜改道，就是第二天只剩散落河滩的箱板和染血车帘，连船家都开始装聋作哑，不敢多问一句。 探子送回的消息说，这支人马不像寻常匪帮，各车之间号令极严，前阵短弓压路，中段刀枪护箱，尾队还留着专门断后的老手。真打起来，他们未必急着和你硬换，只会边退边拖，把人一步步拽进最窄最乱的那段河道。 | U35: 10 | V35: 102 | W35: 0.62 | X35: 红宝石×168（帮会仓库） | Y35: 无 | Z35: 20 | AA35: 是 | AB35: 14 | AC35: data/guild_mission_templates.yaml:L47 | AD35: {} | AE35: {"level":10,"guest_level":102,"guest_bonus":0.62} | AF35: {"key":"guild_supply_escort","name":"血旗镖局风云","description":"血旗镖局表面替各路商号押送金银药材，暗地里却替人收账、截货、买命，沿河几个渡口最近都挂上了他们的旗。凡是不肯交路银的商队，不是半夜改道，就是第二天只剩散落河滩的箱板和染血车帘，连船家都开始装聋作哑，不敢多问一句。\n\n探子送回的消息说，这支人马不像寻常匪帮，各车之间号令极严，前阵短弓压路，中段刀枪护箱，尾队还留着专门断后的老手。真打起来，他们未必急着和你硬换，只会边退边拖，把人一步步拽进最窄最乱的那段河道。\n","difficulty":"intermediate","task_type":"troop","base_duration_seconds":2100,"ruby_reward":168,"weekly_limit":3,"recommended_guest_count":14,"allow_troops":true,"enemy_guests":[{"template_key":"guild_bloodflag_head_escort"},{"template_key":"guild_bloodflag_deputy_escort"},{"template_key":"guild_bloodflag_rearguard_veteran"},{"template_key":"guild_bloodflag_blade_guard"},{"template_key":"guild_bloodflag_blade_guard"},{"template_key":"guild_bloodflag_blade_guard"},{"template_key":"guild_bloodflag_blade_guard"},{"template_key":"guild_bloodflag_bow_guard"},{"template_key":"guild_bloodflag_bow_guard"},{"template_key":"guild_bloodflag_bow_guard"},{"template_key":"guild_bloodflag_bow_guard"},{"template_key":"guild_bloodflag_pathfinder"},{"template_key":"guild_bloodflag_pathfinder"},{"template_key":"guild_bloodflag_escort_master"},{"template_key":"guild_bloodflag_escort_master"},{"template_key":"guild_bloodflag_escort_master"}],"enemy_troops":{"qiang_ba":1180,"jian_hao":980,"divine_archer":1080,"quan_wang":860},"enemy_technology":{"level":10,"guest_level":102,"guest_bonus":0.62},"is_active":true,"sort_weight":20} | AH35: 帮会仓库
A36: 35 | B36: guild_blackwind_assault | C36: 黑风关总攻 | D36: 高级 | E36: troop | F36: 否 | G36: 否 | I36: 3000 | J36: 每日开放 | K36: 无 | L36: =SUMIFS(敌方阵容!$F$2:$F$258,敌方阵容!$A$2:$A$258,B36,敌方阵容!$D$2:$D$258,"门客") -> 22 | M36: =SUMIFS(敌方阵容!$F$2:$F$258,敌方阵容!$A$2:$A$258,B36,敌方阵容!$D$2:$D$258,"护院") -> 6680 | N36: =COUNTIF(任务掉落明细!$B$2:$B$66,B36) -> 1 | O36: =COUNTIFS(任务掉落明细!$B$2:$B$66,B36,任务掉落明细!$X$2:$X$66,1) -> 1 | P36: =COUNTIFS(任务掉落明细!$B$2:$B$66,B36,任务掉落明细!$X$2:$X$66,"<1") -> 0 | Q36: 帮会任务 | R36: 3 | T36: 黑风关原是旧时军镇咽喉，多年废弃后反被各路亡命和旧军头子修成了铁桶。关前壕沟是新翻的，拒马、滚木和石垒顺着山口一层层铺开，城头昼夜轮火不熄；前几次探路的人才看见墙影里箭光一闪，山道上就已经响起调兵铜哨。 更麻烦的是，关内粮械齐备，轮守之人熟悉军阵，能把外墙、甬道和内寨连成一口气。若真要把黑风关从地图上抹去，便不是冲开一道门那么简单，而是要顶着连番反扑一路杀到关楼，把还在运转的整座堡寨硬生生拆开。 | U36: 12 | V36: 108 | W36: 0.96 | X36: 红宝石×288（帮会仓库） | Y36: 无 | Z36: 30 | AA36: 是 | AB36: 18 | AC36: data/guild_mission_templates.yaml:L89 | AD36: {} | AE36: {"level":12,"guest_level":108,"guest_bonus":0.96} | AF36: {"key":"guild_blackwind_assault","name":"黑风关总攻","description":"黑风关原是旧时军镇咽喉，多年废弃后反被各路亡命和旧军头子修成了铁桶。关前壕沟是新翻的，拒马、滚木和石垒顺着山口一层层铺开，城头昼夜轮火不熄；前几次探路的人才看见墙影里箭光一闪，山道上就已经响起调兵铜哨。\n\n更麻烦的是，关内粮械齐备，轮守之人熟悉军阵，能把外墙、甬道和内寨连成一口气。若真要把黑风关从地图上抹去，便不是冲开一道门那么简单，而是要顶着连番反扑一路杀到关楼，把还在运转的整座堡寨硬生生拆开。\n","difficulty":"advanced","task_type":"troop","base_duration_seconds":3000,"ruby_reward":288,"weekly_limit":3,"recommended_guest_count":18,"allow_troops":true,"enemy_guests":[{"template_key":"guild_blackwind_gate_general"},{"template_key":"guild_blackwind_gate_overseer"},{"template_key":"guild_blackwind_iron_guard"},{"template_key":"guild_blackwind_iron_guard"},{"template_key":"guild_blackwind_iron_guard"},{"template_key":"guild_blackwind_bow_captain"},{"template_key":"guild_blackwind_bow_captain"},{"template_key":"guild_blackwind_bow_captain"},{"template_key":"guild_blackwind_assault_blade"},{"template_key":"guild_blackwind_assault_blade"},{"template_key":"guild_blackwind_assault_blade"},{"template_key":"guild_blackwind_assault_blade"},{"template_key":"guild_blackwind_assault_blade"},{"template_key":"guild_blackwind_patrol_captain"},{"template_key":"guild_blackwind_patrol_captain"},{"template_key":"guild_blackwind_guard_soldier"},{"template_key":"guild_blackwind_guard_soldier"},{"template_key":"guild_blackwind_guard_soldier"},{"template_key":"guild_blackwind_spear_soldier"},{"template_key":"guild_blackwind_spear_soldier"},{"template_key":"guild_blackwind_spear_soldier"},{"template_key":"guild_blackwind_spear_soldier"}],"enemy_troops":{"qiang_wang":1700,"jian_sheng":1450,"arrow_god":1620,"quan_sheng":980,"dao_sheng":930},"enemy_technology":{"level":12,"guest_level":108,"guest_bonus":0.96},"is_active":true,"sort_weight":30} | AH36: 帮会仓库

Sheet 任务掉落明细
A1: 序号 | B1: 任务key | C1: 任务名称 | D1: 难度 | E1: 战斗类型 | F1: 防守任务 | G1: 仅门客 | H1: 每日次数 | I1: 配置基础耗时秒 | J1: 开放星期 | K1: 进入消耗 | L1: 掉落类型 | M1: 掉落配置key | N1: 实际掉落key | O1: 实际掉落名称 | P1: 物品类型 | Q1: 稀有度 | R1: 掉落/随机池触发概率 | S1: 数量 | T1: 池内权重 | U1: 是否选择池 | V1: 原始配置 | W1: 池内权重合计 | X1: 单项实际掉落概率 | Y1: 单次胜利期望数量 | Z1: 任务分类 | AA1: 每周次数(帮会) | AB1: 奖励接收方 | AC1: 发奖条件 | AD1: 数据来源
A2: 1 | B2: mid_autumn_moon_palace_trial | C2: 广寒宫试炼 | D2: 中级 | E2: task1 | F2: 否 | G2: 否 | H2: 3 | I2: 1800 | J2: 周二、周四、周六、周日 | K2: 无 | L2: 固定掉落 | M2: silver | N2: silver | O2: 银两 | P2: 资源 | Q2: 资源 | R2: 1 | S2: 40000 | U2: 否 | V2: 40000 | X2: =R2 -> 1 | Y2: =X2*S2 -> 40000 | Z2: 个人任务 | AB2: 挑战者庄园 | AC2: 玩家胜利、非撤退，任务返程/防守结算；宝箱内容另见宝箱奖励明细 | AD2: data/mission_templates.yaml:mid_autumn_moon_palace_trial.drop_table.silver
A3: 2 | B3: mid_autumn_moon_palace_trial | C3: 广寒宫试炼 | D3: 中级 | E3: task1 | F3: 否 | G3: 否 | H3: 3 | I3: 1800 | J3: 周二、周四、周六、周日 | K3: 无 | L3: 固定掉落 | M3: mission_chest_mid_autumn_moon_palace_trial | N3: mission_chest_mid_autumn_moon_palace_trial | O3: 广寒宫试炼宝箱 | P3: loot_box | Q3: blue | R3: 1 | S3: 1 | U3: 否 | V3: 1 | X3: =R3 -> 1 | Y3: =X3*S3 -> 1 | Z3: 个人任务 | AB3: 挑战者庄园 | AC3: 玩家胜利、非撤退，任务返程/防守结算；宝箱内容另见宝箱奖励明细 | AD3: data/mission_templates.yaml:mid_autumn_moon_palace_trial.drop_table.mission_chest_mid_autumn_moon_palace_trial
A4: 3 | B4: kasukabe_daisakusen | C4: 春日部大作战 | D4: 中级 | E4: task1 | F4: 否 | G4: 否 | H4: 3 | I4: 1800 | J4: 周二、周四、周六、周日 | K4: 无 | L4: 固定掉落 | M4: silver | N4: silver | O4: 银两 | P4: 资源 | Q4: 资源 | R4: 1 | S4: 40000 | U4: 否 | V4: 40000 | X4: =R4 -> 1 | Y4: =X4*S4 -> 40000 | Z4: 个人任务 | AB4: 挑战者庄园 | AC4: 玩家胜利、非撤退，任务返程/防守结算；宝箱内容另见宝箱奖励明细 | AD4: data/mission_templates.yaml:kasukabe_daisakusen.drop_table.silver
A5: 4 | B5: kasukabe_daisakusen | C5: 春日部大作战 | D5: 中级 | E5: task1 | F5: 否 | G5: 否 | H5: 3 | I5: 1800 | J5: 周二、周四、周六、周日 | K5: 无 | L5: 固定掉落 | M5: mission_chest_kasukabe_daisakusen | N5: mission_chest_kasukabe_daisakusen | O5: 春日部大作战宝箱 | P5: loot_box | Q5: blue | R5: 1 | S5: 1 | U5: 否 | V5: 1 | X5: =R5 -> 1 | Y5: =X5*S5 -> 1 | Z5: 个人任务 | AB5: 挑战者庄园 | AC5: 玩家胜利、非撤退，任务返程/防守结算；宝箱内容另见宝箱奖励明细 | AD5: data/mission_templates.yaml:kasukabe_daisakusen.drop_table.mission_chest_kasukabe_daisakusen
A6: 5 | B6: huashan_lunjian | C6: 华山论贱 | D6: 初级 | E6: task1 | F6: 否 | G6: 是 | H6: 3 | I6: 1800 | J6: 每日开放 | K6: 无 | L6: 固定掉落 | M6: silver | N6: silver | O6: 银两 | P6: 资源 | Q6: 资源 | R6: 1 | S6: 8000 | U6: 否 | V6: 8000 | X6: =R6 -> 1 | Y6: =X6*S6 -> 8000 | Z6: 个人任务 | AB6: 挑战者庄园 | AC6: 玩家胜利、非撤退，任务返程/防守结算；宝箱内容另见宝箱奖励明细 | AD6: data/mission_templates.yaml:huashan_lunjian.drop_table.silver
A7: 6 | B7: huashan_lunjian | C7: 华山论贱 | D7: 初级 | E7: task1 | F7: 否 | G7: 是 | H7: 3 | I7: 1800 | J7: 每日开放 | K7: 无 | L7: 固定掉落 | M7: mission_chest_huashan_lunjian | N7: mission_chest_huashan_lunjian | O7: 华山论贱宝箱 | P7: loot_box | Q7: green | R7: 1 | S7: 1 | U7: 否 | V7: 1 | X7: =R7 -> 1 | Y7: =X7*S7 -> 1 | Z7: 个人任务 | AB7: 挑战者庄园 | AC7: 玩家胜利、非撤退，任务返程/防守结算；宝箱内容另见宝箱奖励明细 | AD7: data/mission_templates.yaml:huashan_lunjian.drop_table.mission_chest_huashan_lunjian
A8: 7 | B8: wagangzhai_nixi | C8: 瓦岗寨的逆袭 | D8: 中级 | E8: task1 | F8: 是 | G8: 否 | H8: 3 | I8: 1800 | J8: 每日开放 | K8: 无 | L8: 固定掉落 | M8: silver | N8: silver | O8: 银两 | P8: 资源 | Q8: 资源 | R8: 1 | S8: 40000 | U8: 否 | V8: 40000 | X8: =R8 -> 1 | Y8: =X8*S8 -> 40000 | Z8: 个人任务 | AB8: 挑战者庄园 | AC8: 玩家胜利、非撤退，任务返程/防守结算；宝箱内容另见宝箱奖励明细 | AD8: data/mission_templates.yaml:wagangzhai_nixi.drop_table.silver
A9: 8 | B9: wagangzhai_nixi | C9: 瓦岗寨的逆袭 | D9: 中级 | E9: task1 | F9: 是 | G9: 否 | H9: 3 | I9: 1800 | J9: 每日开放 | K9: 无 | L9: 固定掉落 | M9: mission_chest_wagangzhai_nixi | N9: mission_chest_wagangzhai_nixi | O9: 瓦岗寨的逆袭宝箱 | P9: loot_box | Q9: blue | R9: 1 | S9: 1 | U9: 否 | V9: 1 | X9: =R9 -> 1 | Y9: =X9*S9 -> 1 | Z9: 个人任务 | AB9: 挑战者庄园 | AC9: 玩家胜利、非撤退，任务返程/防守结算；宝箱内容另见宝箱奖励明细 | AD9: data/mission_templates.yaml:wagangzhai_nixi.drop_table.mission_chest_wagangzhai_nixi
A10: 9 | B10: jingyanggang | C10: 景阳冈 | D10: 初级 | E10: task1 | F10: 否 | G10: 是 | H10: 3 | I10: 1800 | J10: 每日开放 | K10: 无 | L10: 固定掉落 | M10: silver | N10: silver | O10: 银两 | P10: 资源 | Q10: 资源 | R10: 1 | S10: 7000 | U10: 否 | V10: 7000 | X10: =R10 -> 1 | Y10: =X10*S10 -> 7000 | Z10: 个人任务 | AB10: 挑战者庄园 | AC10: 玩家胜利、非撤退，任务返程/防守结算；宝箱内容另见宝箱奖励明细 | AD10: data/mission_templates.yaml:jingyanggang.drop_table.silver
A11: 10 | B11: jingyanggang | C11: 景阳冈 | D11: 初级 | E11: task1 | F11: 否 | G11: 是 | H11: 3 | I11: 1800 | J11: 每日开放 | K11: 无 | L11: 固定掉落 | M11: mission_chest_jingyanggang | N11: mission_chest_jingyanggang | O11: 景阳冈宝箱 | P11: loot_box | Q11: green | R11: 1 | S11: 1 | U11: 否 | V11: 1 | X11: =R11 -> 1 | Y11: =X11*S11 -> 1 | Z11: 个人任务 | AB11: 挑战者庄园 | AC11: 玩家胜利、非撤退，任务返程/防守结算；宝箱内容另见宝箱奖励明细 | AD11: data/mission_templates.yaml:jingyanggang.drop_table.mission_chest_jingyanggang
A12: 11 | B12: wulongshan | C12: 乌龙山 | D12: 初级 | E12: task1 | F12: 否 | G12: 否 | H12: 3 | I12: 1800 | J12: 每日开放 | K12: 无 | L12: 固定掉落 | M12: silver | N12: silver | O12: 银两 | P12: 资源 | Q12: 资源 | R12: 1 | S12: 15000 | U12: 否 | V12: 15000 | X12: =R12 -> 1 | Y12: =X12*S12 -> 15000 | Z12: 个人任务 | AB12: 挑战者庄园 | AC12: 玩家胜利、非撤退，任务返程/防守结算；宝箱内容另见宝箱奖励明细 | AD12: data/mission_templates.yaml:wulongshan.drop_table.silver
A13: 12 | B13: wulongshan | C13: 乌龙山 | D13: 初级 | E13: task1 | F13: 否 | G13: 否 | H13: 3 | I13: 1800 | J13: 每日开放 | K13: 无 | L13: 固定掉落 | M13: mission_chest_wulongshan | N13: mission_chest_wulongshan | O13: 乌龙山宝箱 | P13: loot_box | Q13: green | R13: 1 | S13: 1 | U13: 否 | V13: 1 | X13: =R13 -> 1 | Y13: =X13*S13 -> 1 | Z13: 个人任务 | AB13: 挑战者庄园 | AC13: 玩家胜利、非撤退，任务返程/防守结算；宝箱内容另见宝箱奖励明细 | AD13: data/mission_templates.yaml:wulongshan.drop_table.mission_chest_wulongshan
... A63: 62 | B63: baimenlou_mingyun_jueze | C63: 飞将浮沉录：白门楼命运抉择 | D63: 高级 | E63: task1 | F63: 否 | G63: 否 | H63: 1 | I63: 2700 | J63: 每日开放 | K63: 虎牢关战旗×1 | L63: 固定掉落 | M63: mission_chest_baimenlou_mingyun_jueze | N63: mission_chest_baimenlou_mingyun_jueze | O63: 白门楼宝箱 | P63: loot_box | Q63: purple | R63: 1 | S63: 1 | U63: 否 | V63: 1 | X63: =R63 -> 1 | Y63: =X63*S63 -> 1 | Z63: 个人任务 | AB63: 挑战者庄园 | AC63: 玩家胜利、非撤退，任务返程/防守结算；宝箱内容另见宝箱奖励明细 | AD63: data/mission_templates.yaml:baimenlou_mingyun_jueze.drop_table.mission_chest_baimenlou_mingyun_jueze
A64: 63 | B64: guild_patrol_alpha | C64: 夜袭乌鳞寨 | D64: 初级 | E64: troop | F64: 否 | G64: 否 | I64: 1500 | J64: 每日开放 | K64: 无 | L64: 帮会固定奖励 | M64: red_ruby | N64: red_ruby | O64: 红宝石 | P64: 资源 | Q64: 稀有/蓝 | R64: 1 | S64: 96 | U64: 否 | V64: 96 | X64: =R64 -> 1 | Y64: =X64*S64 -> 96 | Z64: 帮会任务 | AA64: 3 | AB64: 帮会仓库 | AC64: 帮会任务胜利（attacker），非撤退，结算发放 | AD64: data/guild_mission_templates.yaml:L9:ruby_reward
A65: 64 | B65: guild_supply_escort | C65: 血旗镖局风云 | D65: 中级 | E65: troop | F65: 否 | G65: 否 | I65: 2100 | J65: 每日开放 | K65: 无 | L65: 帮会固定奖励 | M65: red_ruby | N65: red_ruby | O65: 红宝石 | P65: 资源 | Q65: 稀有/蓝 | R65: 1 | S65: 168 | U65: 否 | V65: 168 | X65: =R65 -> 1 | Y65: =X65*S65 -> 168 | Z65: 帮会任务 | AA65: 3 | AB65: 帮会仓库 | AC65: 帮会任务胜利（attacker），非撤退，结算发放 | AD65: data/guild_mission_templates.yaml:L47:ruby_reward
A66: 65 | B66: guild_blackwind_assault | C66: 黑风关总攻 | D66: 高级 | E66: troop | F66: 否 | G66: 否 | I66: 3000 | J66: 每日开放 | K66: 无 | L66: 帮会固定奖励 | M66: red_ruby | N66: red_ruby | O66: 红宝石 | P66: 资源 | Q66: 稀有/蓝 | R66: 1 | S66: 288 | U66: 否 | V66: 288 | X66: =R66 -> 1 | Y66: =X66*S66 -> 288 | Z66: 帮会任务 | AA66: 3 | AB66: 帮会仓库 | AC66: 帮会任务胜利（attacker），非撤退，结算发放 | AD66: data/guild_mission_templates.yaml:L89:ruby_reward

Sheet 掉落物反查
A1: 物品key | B1: 物品名称 | C1: 物品类型 | D1: 稀有度 | E1: 任务key | F1: 任务名称 | G1: 掉落类型 | H1: 单项实际掉落概率 | I1: 数量 | J1: 掉落配置key | K1: 任务分类 | L1: 奖励接收方 | M1: 单次胜利期望数量 | N1: 数据来源
A2: silver | B2: 银两 | C2: 资源 | D2: 资源 | E2: mid_autumn_moon_palace_trial | F2: 广寒宫试炼 | G2: 固定掉落 | H2: ='任务掉落明细'!X2 -> 1 | I2: 40000 | J2: silver | K2: 个人任务 | L2: 挑战者庄园 | M2: ='任务掉落明细'!Y2 -> 40000 | N2: data/mission_templates.yaml:mid_autumn_moon_palace_trial.drop_table.silver
A3: mission_chest_mid_autumn_moon_palace_trial | B3: 广寒宫试炼宝箱 | C3: loot_box | D3: blue | E3: mid_autumn_moon_palace_trial | F3: 广寒宫试炼 | G3: 固定掉落 | H3: ='任务掉落明细'!X3 -> 1 | I3: 1 | J3: mission_chest_mid_autumn_moon_palace_trial | K3: 个人任务 | L3: 挑战者庄园 | M3: ='任务掉落明细'!Y3 -> 1 | N3: data/mission_templates.yaml:mid_autumn_moon_palace_trial.drop_table.mission_chest_mid_autumn_moon_palace_trial
A4: silver | B4: 银两 | C4: 资源 | D4: 资源 | E4: kasukabe_daisakusen | F4: 春日部大作战 | G4: 固定掉落 | H4: ='任务掉落明细'!X4 -> 1 | I4: 40000 | J4: silver | K4: 个人任务 | L4: 挑战者庄园 | M4: ='任务掉落明细'!Y4 -> 40000 | N4: data/mission_templates.yaml:kasukabe_daisakusen.drop_table.silver
A5: mission_chest_kasukabe_daisakusen | B5: 春日部大作战宝箱 | C5: loot_box | D5: blue | E5: kasukabe_daisakusen | F5: 春日部大作战 | G5: 固定掉落 | H5: ='任务掉落明细'!X5 -> 1 | I5: 1 | J5: mission_chest_kasukabe_daisakusen | K5: 个人任务 | L5: 挑战者庄园 | M5: ='任务掉落明细'!Y5 -> 1 | N5: data/mission_templates.yaml:kasukabe_daisakusen.drop_table.mission_chest_kasukabe_daisakusen
A6: silver | B6: 银两 | C6: 资源 | D6: 资源 | E6: huashan_lunjian | F6: 华山论贱 | G6: 固定掉落 | H6: ='任务掉落明细'!X6 -> 1 | I6: 8000 | J6: silver | K6: 个人任务 | L6: 挑战者庄园 | M6: ='任务掉落明细'!Y6 -> 8000 | N6: data/mission_templates.yaml:huashan_lunjian.drop_table.silver
A7: mission_chest_huashan_lunjian | B7: 华山论贱宝箱 | C7: loot_box | D7: green | E7: huashan_lunjian | F7: 华山论贱 | G7: 固定掉落 | H7: ='任务掉落明细'!X7 -> 1 | I7: 1 | J7: mission_chest_huashan_lunjian | K7: 个人任务 | L7: 挑战者庄园 | M7: ='任务掉落明细'!Y7 -> 1 | N7: data/mission_templates.yaml:huashan_lunjian.drop_table.mission_chest_huashan_lunjian
A8: silver | B8: 银两 | C8: 资源 | D8: 资源 | E8: wagangzhai_nixi | F8: 瓦岗寨的逆袭 | G8: 固定掉落 | H8: ='任务掉落明细'!X8 -> 1 | I8: 40000 | J8: silver | K8: 个人任务 | L8: 挑战者庄园 | M8: ='任务掉落明细'!Y8 -> 40000 | N8: data/mission_templates.yaml:wagangzhai_nixi.drop_table.silver
A9: mission_chest_wagangzhai_nixi | B9: 瓦岗寨的逆袭宝箱 | C9: loot_box | D9: blue | E9: wagangzhai_nixi | F9: 瓦岗寨的逆袭 | G9: 固定掉落 | H9: ='任务掉落明细'!X9 -> 1 | I9: 1 | J9: mission_chest_wagangzhai_nixi | K9: 个人任务 | L9: 挑战者庄园 | M9: ='任务掉落明细'!Y9 -> 1 | N9: data/mission_templates.yaml:wagangzhai_nixi.drop_table.mission_chest_wagangzhai_nixi
A10: silver | B10: 银两 | C10: 资源 | D10: 资源 | E10: jingyanggang | F10: 景阳冈 | G10: 固定掉落 | H10: ='任务掉落明细'!X10 -> 1 | I10: 7000 | J10: silver | K10: 个人任务 | L10: 挑战者庄园 | M10: ='任务掉落明细'!Y10 -> 7000 | N10: data/mission_templates.yaml:jingyanggang.drop_table.silver
A11: mission_chest_jingyanggang | B11: 景阳冈宝箱 | C11: loot_box | D11: green | E11: jingyanggang | F11: 景阳冈 | G11: 固定掉落 | H11: ='任务掉落明细'!X11 -> 1 | I11: 1 | J11: mission_chest_jingyanggang | K11: 个人任务 | L11: 挑战者庄园 | M11: ='任务掉落明细'!Y11 -> 1 | N11: data/mission_templates.yaml:jingyanggang.drop_table.mission_chest_jingyanggang
A12: silver | B12: 银两 | C12: 资源 | D12: 资源 | E12: wulongshan | F12: 乌龙山 | G12: 固定掉落 | H12: ='任务掉落明细'!X12 -> 1 | I12: 15000 | J12: silver | K12: 个人任务 | L12: 挑战者庄园 | M12: ='任务掉落明细'!Y12 -> 15000 | N12: data/mission_templates.yaml:wulongshan.drop_table.silver
A13: mission_chest_wulongshan | B13: 乌龙山宝箱 | C13: loot_box | D13: green | E13: wulongshan | F13: 乌龙山 | G13: 固定掉落 | H13: ='任务掉落明细'!X13 -> 1 | I13: 1 | J13: mission_chest_wulongshan | K13: 个人任务 | L13: 挑战者庄园 | M13: ='任务掉落明细'!Y13 -> 1 | N13: data/mission_templates.yaml:wulongshan.drop_table.mission_chest_wulongshan
... A66: red_ruby | B66: 红宝石 | C66: 资源 | D66: 稀有/蓝 | E66: guild_blackwind_assault | F66: 黑风关总攻 | G66: 帮会固定奖励 | H66: ='任务掉落明细'!X66 -> 1 | I66: 288 | J66: red_ruby | K66: 帮会任务 | L66: 帮会仓库 | M66: ='任务掉落明细'!Y66 -> 288 | N66: data/guild_mission_templates.yaml:L89:ruby_reward

Sheet 敌方阵容
A1: 任务key | B1: 任务名称 | C1: 任务分类 | D1: 单位类型 | E1: 单位key | F1: 数量 | G1: 单位名称 | H1: 门客技能 | I1: 统一科技等级 | J1: 门客等级 | K1: 门客属性加成 | L1: 数据来源 | M1: 原始单位配置(JSON)
A2: mid_autumn_moon_palace_trial | B2: 广寒宫试炼 | C2: 个人任务 | D2: 门客 | E2: myth_moon_jade_rabbit | F2: 1 | G2: 玉兔 | H2: 使用模板默认技能 | I2: 7 | J2: 60 | K2: 0.12 | L2: data/mission_templates.yaml:L139:enemy_guests | M2: {"key":"myth_moon_jade_rabbit","label":"玉兔"}
A3: mid_autumn_moon_palace_trial | B3: 广寒宫试炼 | C3: 个人任务 | D3: 门客 | E3: myth_moon_wu_gang | F3: 1 | G3: 吴刚 | H3: 使用模板默认技能 | I3: 7 | J3: 60 | K3: 0.12 | L3: data/mission_templates.yaml:L139:enemy_guests | M3: {"key":"myth_moon_wu_gang","label":"吴刚"}
A4: mid_autumn_moon_palace_trial | B4: 广寒宫试炼 | C4: 个人任务 | D4: 门客 | E4: hist_xianqin_0413 | F4: 1 | G4: 嫦娥 | H4: 使用模板默认技能 | I4: 7 | J4: 60 | K4: 0.12 | L4: data/mission_templates.yaml:L139:enemy_guests | M4: {"key":"hist_xianqin_0413","label":"嫦娥"}
A5: mid_autumn_moon_palace_trial | B5: 广寒宫试炼 | C5: 个人任务 | D5: 护院 | E5: quan_wang | F5: 300 | G5: 拳王 | I5: 7 | L5: data/mission_templates.yaml:L139:enemy_troops | M5: {"quan_wang":300}
A6: mid_autumn_moon_palace_trial | B6: 广寒宫试炼 | C6: 个人任务 | D6: 护院 | E6: jian_hao | F6: 300 | G6: 剑豪 | I6: 7 | L6: data/mission_templates.yaml:L139:enemy_troops | M6: {"jian_hao":300}
A7: mid_autumn_moon_palace_trial | B7: 广寒宫试炼 | C7: 个人任务 | D7: 护院 | E7: divine_archer | F7: 200 | G7: 神箭手 | I7: 7 | L7: data/mission_templates.yaml:L139:enemy_troops | M7: {"divine_archer":200}
A8: kasukabe_daisakusen | B8: 春日部大作战 | C8: 个人任务 | D8: 门客 | E8: task_kasukabe_patrol_captain | F8: 1 | G8: 春日部巡逻队长 | H8: 使用模板默认技能 | I8: 7 | J8: 60 | K8: 0.12 | L8: data/mission_templates.yaml:L206:enemy_guests | M8: {"key":"task_kasukabe_patrol_captain","label":"春日部巡逻队长"}
A9: kasukabe_daisakusen | B9: 春日部大作战 | C9: 个人任务 | D9: 门客 | E9: task_kasukabe_toy_crocodile | F9: 1 | G9: 玩具机关鳄鱼 | H9: 使用模板默认技能 | I9: 7 | J9: 60 | K9: 0.12 | L9: data/mission_templates.yaml:L206:enemy_guests | M9: {"key":"task_kasukabe_toy_crocodile","label":"玩具机关鳄鱼"}
A10: kasukabe_daisakusen | B10: 春日部大作战 | C10: 个人任务 | D10: 门客 | E10: task_kasukabe_defense_member | F10: 1 | G10: 迷路的防卫队员 | H10: 使用模板默认技能 | I10: 7 | J10: 60 | K10: 0.12 | L10: data/mission_templates.yaml:L206:enemy_guests | M10: {"key":"task_kasukabe_defense_member","label":"迷路的防卫队员"}
A11: kasukabe_daisakusen | B11: 春日部大作战 | C11: 个人任务 | D11: 门客 | E11: task_kasukabe_crayon_clone | F11: 1 | G11: 蜡笔恶作剧分身 | H11: 使用模板默认技能 | I11: 7 | J11: 60 | K11: 0.12 | L11: data/mission_templates.yaml:L206:enemy_guests | M11: {"key":"task_kasukabe_crayon_clone","label":"蜡笔恶作剧分身"}
A12: kasukabe_daisakusen | B12: 春日部大作战 | C12: 个人任务 | D12: 门客 | E12: task_kasukabe_doodle_boss | F12: 1 | G12: 涂鸦大魔王 | H12: 使用模板默认技能 | I12: 7 | J12: 60 | K12: 0.12 | L12: data/mission_templates.yaml:L206:enemy_guests | M12: {"key":"task_kasukabe_doodle_boss","label":"涂鸦大魔王"}
A13: kasukabe_daisakusen | B13: 春日部大作战 | C13: 个人任务 | D13: 护院 | E13: quan_wang | F13: 300 | G13: 拳王 | I13: 7 | L13: data/mission_templates.yaml:L206:enemy_troops | M13: {"quan_wang":300}
A14: kasukabe_daisakusen | B14: 春日部大作战 | C14: 个人任务 | D14: 护院 | E14: archer | F14: 300 | G14: 弓箭手 | I14: 7 | L14: data/mission_templates.yaml:L206:enemy_troops | M14: {"archer":300}
A15: kasukabe_daisakusen | B15: 春日部大作战 | C15: 个人任务 | D15: 护院 | E15: dao_ba | F15: 200 | G15: 刀霸 | I15: 7 | L15: data/mission_templates.yaml:L206:enemy_troops | M15: {"dao_ba":200}
A16: huashan_lunjian | B16: 华山论贱 | C16: 个人任务 | D16: 门客 | E16: task_huashan_jianwang | F16: 1 | G16: 贱王之王 | H16: 使用模板默认技能 | I16: 2 | J16: 12 | K16: 0 | L16: data/mission_templates.yaml:L287:enemy_guests | M16: {"key":"task_huashan_jianwang","label":"贱王之王"}
A17: huashan_lunjian | B17: 华山论贱 | C17: 个人任务 | D17: 门客 | E17: task_huashan_jianjing | F17: 1 | G17: 顶级贱精 | H17: 使用模板默认技能 | I17: 2 | J17: 12 | K17: 0 | L17: data/mission_templates.yaml:L287:enemy_guests | M17: {"key":"task_huashan_jianjing","label":"顶级贱精"}
A18: huashan_lunjian | B18: 华山论贱 | C18: 个人任务 | D18: 门客 | E18: task_huashan_jianjing | F18: 1 | G18: 顶级贱精 | H18: 使用模板默认技能 | I18: 2 | J18: 12 | K18: 0 | L18: data/mission_templates.yaml:L287:enemy_guests | M18: {"key":"task_huashan_jianjing","label":"顶级贱精"}
A19: huashan_lunjian | B19: 华山论贱 | C19: 个人任务 | D19: 门客 | E19: task_huashan_audience_a | F19: 1 | G19: 观众甲 | H19: 使用模板默认技能 | I19: 2 | J19: 12 | K19: 0 | L19: data/mission_templates.yaml:L287:enemy_guests | M19: {"key":"task_huashan_audience_a","label":"观众甲"}
A20: wagangzhai_nixi | B20: 瓦岗寨的逆袭 | C20: 个人任务 | D20: 门客 | E20: hist_suitang_0162_zhairang | F20: 1 | G20: 翟让 | H20: 唐僧说禅 | I20: 10 | J20: 100 | K20: 0.3 | L20: data/mission_templates.yaml:L326:enemy_guests | M20: {"key":"hist_suitang_0162_zhairang","skills":["tangseng_sermon"]}
A21: wagangzhai_nixi | B21: 瓦岗寨的逆袭 | C21: 个人任务 | D21: 门客 | E21: hero_qin_shubao | F21: 1 | G21: 秦叔宝 | H21: 梵天真火 | I21: 10 | J21: 100 | K21: 0.3 | L21: data/mission_templates.yaml:L326:enemy_guests | M21: {"key":"hero_qin_shubao","skills":["brahma_true_fire"]}
A22: wagangzhai_nixi | B22: 瓦岗寨的逆袭 | C22: 个人任务 | D22: 门客 | E22: hist_suitang_0164_shanxiongxin | F22: 1 | G22: 单雄信 | H22: 使用模板默认技能 | I22: 10 | J22: 100 | K22: 0.3 | L22: data/mission_templates.yaml:L326:enemy_guests | M22: "hist_suitang_0164_shanxiongxin"
A23: wagangzhai_nixi | B23: 瓦岗寨的逆袭 | C23: 个人任务 | D23: 门客 | E23: hist_suitang_0165_wangbodang | F23: 1 | G23: 王伯当 | H23: 使用模板默认技能 | I23: 10 | J23: 100 | K23: 0.3 | L23: data/mission_templates.yaml:L326:enemy_guests | M23: "hist_suitang_0165_wangbodang"
A24: wagangzhai_nixi | B24: 瓦岗寨的逆袭 | C24: 个人任务 | D24: 门客 | E24: hero_luo_cheng | F24: 1 | G24: 罗成 | H24: 使用模板默认技能 | I24: 10 | J24: 100 | K24: 0.3 | L24: data/mission_templates.yaml:L326:enemy_guests | M24: "hero_luo_cheng"
A25: wagangzhai_nixi | B25: 瓦岗寨的逆袭 | C25: 个人任务 | D25: 门客 | E25: hero_cheng_yaojin | F25: 1 | G25: 程咬金 | H25: 使用模板默认技能 | I25: 10 | J25: 100 | K25: 0.3 | L25: data/mission_templates.yaml:L326:enemy_guests | M25: "hero_cheng_yaojin"
A26: wagangzhai_nixi | B26: 瓦岗寨的逆袭 | C26: 个人任务 | D26: 护院 | E26: arrow_god | F26: 800 | G26: 箭神 | I26: 10 | L26: data/mission_templates.yaml:L326:enemy_troops | M26: {"arrow_god":800}
A27: wagangzhai_nixi | B27: 瓦岗寨的逆袭 | C27: 个人任务 | D27: 护院 | E27: quan_sheng | F27: 800 | G27: 拳圣 | I27: 10 | L27: data/mission_templates.yaml:L326:enemy_troops | M27: {"quan_sheng":800}
A28: wagangzhai_nixi | B28: 瓦岗寨的逆袭 | C28: 个人任务 | D28: 护院 | E28: qiang_wang | F28: 800 | G28: 枪王 | I28: 10 | L28: data/mission_templates.yaml:L326:enemy_troops | M28: {"qiang_wang":800}
A29: jingyanggang | B29: 景阳冈 | C29: 个人任务 | D29: 门客 | E29: task_jingyang_tiger | F29: 1 | G29: 猛虎 | H29: 使用模板默认技能 | I29: 3 | J29: 15 | K29: 0.02 | L29: data/mission_templates.yaml:L379:enemy_guests | M29: {"key":"task_jingyang_tiger","label":"猛虎"}
A30: wulongshan | B30: 乌龙山 | C30: 个人任务 | D30: 门客 | E30: task_wulong_bandit_chief_zuanshanbao | F30: 1 | G30: 钻山豹 | H30: 使用模板默认技能 | I30: 4 | J30: 20 | K30: 0.04 | L30: data/mission_templates.yaml:L408:enemy_guests | M30: {"key":"task_wulong_bandit_chief_zuanshanbao","label":"钻山豹"}
A31: wulongshan | B31: 乌龙山 | C31: 个人任务 | D31: 门客 | E31: task_wulong_bandit_chief_zuoshandiao | F31: 1 | G31: 座山雕 | H31: 使用模板默认技能 | I31: 4 | J31: 20 | K31: 0.04 | L31: data/mission_templates.yaml:L408:enemy_guests | M31: {"key":"task_wulong_bandit_chief_zuoshandiao","label":"座山雕"}
A32: wulongshan | B32: 乌龙山 | C32: 个人任务 | D32: 护院 | E32: qiang_ke | F32: 200 | G32: 枪客 | I32: 4 | L32: data/mission_templates.yaml:L408:enemy_troops | M32: {"qiang_ke":200}
A33: wagangzhai | B33: 瓦岗寨 | C33: 个人任务 | D33: 门客 | E33: hero_cheng_yaojin | F33: 1 | G33: 程咬金 | H33: 使用模板默认技能 | I33: 5 | J33: 35 | K33: 0.1 | L33: data/mission_templates.yaml:L444:enemy_guests | M33: "hero_cheng_yaojin"
A34: wagangzhai | B34: 瓦岗寨 | C34: 个人任务 | D34: 门客 | E34: hist_suitang_0162_zhairang | F34: 1 | G34: 翟让 | H34: 使用模板默认技能 | I34: 5 | J34: 35 | K34: 0.1 | L34: data/mission_templates.yaml:L444:enemy_guests | M34: "hist_suitang_0162_zhairang"
A35: wagangzhai | B35: 瓦岗寨 | C35: 个人任务 | D35: 护院 | E35: jian_xia | F35: 400 | G35: 剑侠 | I35: 5 | L35: data/mission_templates.yaml:L444:enemy_troops | M35: {"jian_xia":400}
A36: fugui_shanzhuang | B36: 富贵山庄 | C36: 个人任务 | D36: 门客 | E36: task_fugui_instructor | F36: 1 | G36: 武师教头 | H36: 使用模板默认技能 | I36: 3 | J36: 40 | K36: 0.05 | L36: data/mission_templates.yaml:L482:enemy_guests | M36: {"key":"task_fugui_instructor","label":"武师教头"}
A37: shizipo_heidian | B37: 十字坡黑店 | C37: 个人任务 | D37: 门客 | E37: task_shizipo_sun_erniang | F37: 1 | G37: 孙二娘 | H37: 使用模板默认技能 | I37: 6 | J37: 70 | K37: 0.1 | L37: data/mission_templates.yaml:L514:enemy_guests | M37: {"key":"task_shizipo_sun_erniang","label":"孙二娘"}
A38: shizipo_heidian | B38: 十字坡黑店 | C38: 个人任务 | D38: 门客 | E38: task_shizipo_zhang_qing | F38: 1 | G38: 张青 | H38: 使用模板默认技能 | I38: 6 | J38: 70 | K38: 0.1 | L38: data/mission_templates.yaml:L514:enemy_guests | M38: {"key":"task_shizipo_zhang_qing","label":"张青"}
A39: shizipo_heidian | B39: 十字坡黑店 | C39: 个人任务 | D39: 护院 | E39: quan_wang | F39: 300 | G39: 拳王 | I39: 6 | L39: data/mission_templates.yaml:L514:enemy_troops | M39: {"quan_wang":300}
A40: shizipo_heidian | B40: 十字坡黑店 | C40: 个人任务 | D40: 护院 | E40: divine_archer | F40: 300 | G40: 神箭手 | I40: 6 | L40: data/mission_templates.yaml:L514:enemy_troops | M40: {"divine_archer":300}
A41: shizipo_heidian | B41: 十字坡黑店 | C41: 个人任务 | D41: 护院 | E41: dao_ba | F41: 100 | G41: 刀霸 | I41: 6 | L41: data/mission_templates.yaml:L514:enemy_troops | M41: {"dao_ba":100}
A42: shanhaiguan | B42: 山海关 | C42: 个人任务 | D42: 门客 | E42: hist_mingqing_0230 | F42: 1 | G42: 祖大寿 | H42: 使用模板默认技能 | I42: 7 | J42: 70 | K42: 0.18 | L42: data/mission_templates.yaml:L559:enemy_guests | M42: "hist_mingqing_0230"
A43: shanhaiguan | B43: 山海关 | C43: 个人任务 | D43: 门客 | E43: hist_mingqing_0054 | F43: 1 | G43: 吴三桂 | H43: 使用模板默认技能 | I43: 7 | J43: 70 | K43: 0.18 | L43: data/mission_templates.yaml:L559:enemy_guests | M43: "hist_mingqing_0054"
A44: shanhaiguan | B44: 山海关 | C44: 个人任务 | D44: 护院 | E44: jian_sheng | F44: 500 | G44: 剑圣 | I44: 7 | L44: data/mission_templates.yaml:L559:enemy_troops | M44: {"jian_sheng":500}
A45: shanhaiguan | B45: 山海关 | C45: 个人任务 | D45: 护院 | E45: quan_wang | F45: 500 | G45: 拳王 | I45: 7 | L45: data/mission_templates.yaml:L559:enemy_troops | M45: {"quan_wang":500}
A46: shanhaiguan | B46: 山海关 | C46: 个人任务 | D46: 护院 | E46: qiang_ba | F46: 500 | G46: 枪霸 | I46: 7 | L46: data/mission_templates.yaml:L559:enemy_troops | M46: {"qiang_ba":500}
A47: shiren_daochang | B47: 十人道场 | C47: 个人任务 | D47: 门客 | E47: hero_du_sha | F47: 1 | G47: 杜杀 | H47: 使用模板默认技能 | I47: 6 | J47: 55 | K47: 0.08 | L47: data/mission_templates.yaml:L607:enemy_guests | M47: "hero_du_sha"
A48: shiren_daochang | B48: 十人道场 | C48: 个人任务 | D48: 门客 | E48: hero_li_dazui | F48: 1 | G48: 李大嘴 | H48: 使用模板默认技能 | I48: 6 | J48: 55 | K48: 0.08 | L48: data/mission_templates.yaml:L607:enemy_guests | M48: "hero_li_dazui"
A49: shiren_daochang | B49: 十人道场 | C49: 个人任务 | D49: 门客 | E49: hero_hahaer | F49: 1 | G49: 哈哈儿 | H49: 使用模板默认技能 | I49: 6 | J49: 55 | K49: 0.08 | L49: data/mission_templates.yaml:L607:enemy_guests | M49: "hero_hahaer"
A50: shiren_daochang | B50: 十人道场 | C50: 个人任务 | D50: 门客 | E50: hero_tu_jiaojiao | F50: 1 | G50: 屠娇娇 | H50: 使用模板默认技能 | I50: 6 | J50: 55 | K50: 0.08 | L50: data/mission_templates.yaml:L607:enemy_guests | M50: "hero_tu_jiaojiao"
A51: shiren_daochang | B51: 十人道场 | C51: 个人任务 | D51: 门客 | E51: hero_yin_jiuyou | F51: 1 | G51: 阴九幽 | H51: 使用模板默认技能 | I51: 6 | J51: 55 | K51: 0.08 | L51: data/mission_templates.yaml:L607:enemy_guests | M51: "hero_yin_jiuyou"
A52: shiren_daochang | B52: 十人道场 | C52: 个人任务 | D52: 门客 | E52: task_shiren_xiaomimi | F52: 1 | G52: 萧咪咪 | H52: 使用模板默认技能 | I52: 6 | J52: 55 | K52: 0.08 | L52: data/mission_templates.yaml:L607:enemy_guests | M52: {"key":"task_shiren_xiaomimi","label":"萧咪咪"}
A53: shiren_daochang | B53: 十人道场 | C53: 个人任务 | D53: 门客 | E53: task_shiren_xuanyuansanguang | F53: 1 | G53: 轩辕三光 | H53: 使用模板默认技能 | I53: 6 | J53: 55 | K53: 0.08 | L53: data/mission_templates.yaml:L607:enemy_guests | M53: {"key":"task_shiren_xuanyuansanguang","label":"轩辕三光"}
A54: shiren_daochang | B54: 十人道场 | C54: 个人任务 | D54: 门客 | E54: task_shiren_tiezhan | F54: 1 | G54: 铁战 | H54: 使用模板默认技能 | I54: 6 | J54: 55 | K54: 0.08 | L54: data/mission_templates.yaml:L607:enemy_guests | M54: {"key":"task_shiren_tiezhan","label":"铁战"}
A55: shiren_daochang | B55: 十人道场 | C55: 个人任务 | D55: 门客 | E55: hero_bai_kaixin | F55: 1 | G55: 白开心 | H55: 使用模板默认技能 | I55: 6 | J55: 55 | K55: 0.08 | L55: data/mission_templates.yaml:L607:enemy_guests | M55: "hero_bai_kaixin"
A56: shiren_daochang | B56: 十人道场 | C56: 个人任务 | D56: 门客 | E56: task_shiren_luoshixiongdi | F56: 1 | G56: 罗氏兄弟 | H56: 使用模板默认技能 | I56: 6 | J56: 55 | K56: 0.08 | L56: data/mission_templates.yaml:L607:enemy_guests | M56: {"key":"task_shiren_luoshixiongdi","label":"罗氏兄弟"}
A57: jiguanshou_chuxian | B57: 机关兽初现 | C57: 个人任务 | D57: 门客 | E57: task_mechanism_cat | F57: 1 | G57: 改装机械猫 | H57: 使用模板默认技能 | I57: 7 | J57: 35 | K57: 0.12 | L57: data/mission_templates.yaml:L655:enemy_guests | M57: {"key":"task_mechanism_cat","label":"改装机械猫"}
A58: jiguanshou_chuxian | B58: 机关兽初现 | C58: 个人任务 | D58: 门客 | E58: task_mechanism_cat | F58: 1 | G58: 改装机械猫 | H58: 使用模板默认技能 | I58: 7 | J58: 35 | K58: 0.12 | L58: data/mission_templates.yaml:L655:enemy_guests | M58: {"key":"task_mechanism_cat","label":"改装机械猫"}
... A85: jiguan_chuniao | B85: 机关雏鸟 | C85: 个人任务 | D85: 门客 | E85: task_mechanism_bird | F85: 1 | G85: 黑衣人 | H85: 使用模板默认技能 | I85: 7 | J85: 60 | K85: 0.1 | L85: data/mission_templates.yaml:L830:enemy_guests | M85: {"key":"task_mechanism_bird","label":"黑衣人"}
A86: jiguan_chuniao | B86: 机关雏鸟 | C86: 个人任务 | D86: 护院 | E86: qiang_wang | F86: 300 | G86: 枪王 | I86: 7 | L86: data/mission_templates.yaml:L830:enemy_troops | M86: {"qiang_wang":300}
A87: jiguan_chuniao | B87: 机关雏鸟 | C87: 个人任务 | D87: 护院 | E87: jian_sheng | F87: 300 | G87: 剑圣 | I87: 7 | L87: data/mission_templates.yaml:L830:enemy_troops | M87: {"jian_sheng":300}
A88: dongtian_fudi | B88: 洞天福地 | C88: 个人任务 | D88: 门客 | E88: task_heaven_cave_sentinel | F88: 1 | G88: 金甲神兵 | H88: 使用模板默认技能 | I88: 9 | J88: 80 | K88: 0.26 | L88: data/mission_templates.yaml:L873:enemy_guests | M88: {"key":"task_heaven_cave_sentinel","label":"金甲神兵"}
A89: dongtian_fudi | B89: 洞天福地 | C89: 个人任务 | D89: 门客 | E89: task_heaven_cave_sentinel | F89: 1 | G89: 金甲神兵 | H89: 使用模板默认技能 | I89: 9 | J89: 80 | K89: 0.26 | L89: data/mission_templates.yaml:L873:enemy_guests | M89: {"key":"task_heaven_cave_sentinel","label":"金甲神兵"}
A90: dongtian_fudi | B90: 洞天福地 | C90: 个人任务 | D90: 护院 | E90: arrow_god | F90: 300 | G90: 箭神 | I90: 9 | L90: data/mission_templates.yaml:L873:enemy_troops | M90: {"arrow_god":300}
A91: dongtian_fudi | B91: 洞天福地 | C91: 个人任务 | D91: 护院 | E91: quan_sheng | F91: 700 | G91: 拳圣 | I91: 9 | L91: data/mission_templates.yaml:L873:enemy_troops | M91: {"quan_sheng":700}
A92: jiufeng_feihuan | B92: 九峰匪患 | C92: 个人任务 | D92: 门客 | E92: task_nine_peaks_bandit | F92: 1 | G92: 土匪 | H92: 使用模板默认技能 | I92: 6 | J92: 58 | K92: 0.12 | L92: data/mission_templates.yaml:L908:enemy_guests | M92: {"key":"task_nine_peaks_bandit","label":"土匪"}
A93: jiufeng_feihuan | B93: 九峰匪患 | C93: 个人任务 | D93: 门客 | E93: task_nine_peaks_bandit | F93: 1 | G93: 土匪 | H93: 使用模板默认技能 | I93: 6 | J93: 58 | K93: 0.12 | L93: data/mission_templates.yaml:L908:enemy_guests | M93: {"key":"task_nine_peaks_bandit","label":"土匪"}
A94: jiufeng_feihuan | B94: 九峰匪患 | C94: 个人任务 | D94: 门客 | E94: task_nine_peaks_bandit | F94: 1 | G94: 土匪 | H94: 使用模板默认技能 | I94: 6 | J94: 58 | K94: 0.12 | L94: data/mission_templates.yaml:L908:enemy_guests | M94: {"key":"task_nine_peaks_bandit","label":"土匪"}
A95: jiufeng_feihuan | B95: 九峰匪患 | C95: 个人任务 | D95: 护院 | E95: quan_sheng | F95: 500 | G95: 拳圣 | I95: 6 | L95: data/mission_templates.yaml:L908:enemy_troops | M95: {"quan_sheng":500}
A96: jiufeng_feihuan | B96: 九峰匪患 | C96: 个人任务 | D96: 护院 | E96: arrow_god | F96: 100 | G96: 箭神 | I96: 6 | L96: data/mission_templates.yaml:L908:enemy_troops | M96: {"arrow_god":100}
A97: taozi_fenban | B97: 我的桃子分你一半 | C97: 个人任务 | D97: 门客 | E97: task_orchard_wraith | F97: 1 | G97: 孤魂野鬼 | H97: 使用模板默认技能 | I97: 3 | J97: 40 | K97: 0.06 | L97: data/mission_templates.yaml:L951:enemy_guests | M97: {"key":"task_orchard_wraith","label":"孤魂野鬼"}
A98: taozi_fenban | B98: 我的桃子分你一半 | C98: 个人任务 | D98: 门客 | E98: task_orchard_wraith | F98: 1 | G98: 孤魂野鬼 | H98: 使用模板默认技能 | I98: 3 | J98: 40 | K98: 0.06 | L98: data/mission_templates.yaml:L951:enemy_guests | M98: {"key":"task_orchard_wraith","label":"孤魂野鬼"}
A99: taozi_fenban | B99: 我的桃子分你一半 | C99: 个人任务 | D99: 门客 | E99: task_orchard_wraith | F99: 1 | G99: 孤魂野鬼 | H99: 使用模板默认技能 | I99: 3 | J99: 40 | K99: 0.06 | L99: data/mission_templates.yaml:L951:enemy_guests | M99: {"key":"task_orchard_wraith","label":"孤魂野鬼"}
A100: taozi_fenban | B100: 我的桃子分你一半 | C100: 个人任务 | D100: 门客 | E100: task_orchard_wraith | F100: 1 | G100: 孤魂野鬼 | H100: 使用模板默认技能 | I100: 3 | J100: 40 | K100: 0.06 | L100: data/mission_templates.yaml:L951:enemy_guests | M100: {"key":"task_orchard_wraith","label":"孤魂野鬼"}
A101: taozi_fenban | B101: 我的桃子分你一半 | C101: 个人任务 | D101: 门客 | E101: task_orchard_wraith | F101: 1 | G101: 孤魂野鬼 | H101: 使用模板默认技能 | I101: 3 | J101: 40 | K101: 0.06 | L101: data/mission_templates.yaml:L951:enemy_guests | M101: {"key":"task_orchard_wraith","label":"孤魂野鬼"}
A102: taozi_fenban | B102: 我的桃子分你一半 | C102: 个人任务 | D102: 门客 | E102: task_orchard_wraith | F102: 1 | G102: 孤魂野鬼 | H102: 使用模板默认技能 | I102: 3 | J102: 40 | K102: 0.06 | L102: data/mission_templates.yaml:L951:enemy_guests | M102: {"key":"task_orchard_wraith","label":"孤魂野鬼"}
A103: taozi_fenban | B103: 我的桃子分你一半 | C103: 个人任务 | D103: 门客 | E103: task_orchard_wraith | F103: 1 | G103: 孤魂野鬼 | H103: 使用模板默认技能 | I103: 3 | J103: 40 | K103: 0.06 | L103: data/mission_templates.yaml:L951:enemy_guests | M103: {"key":"task_orchard_wraith","label":"孤魂野鬼"}
A104: taozi_fenban | B104: 我的桃子分你一半 | C104: 个人任务 | D104: 门客 | E104: task_orchard_wraith | F104: 1 | G104: 孤魂野鬼 | H104: 使用模板默认技能 | I104: 3 | J104: 40 | K104: 0.06 | L104: data/mission_templates.yaml:L951:enemy_guests | M104: {"key":"task_orchard_wraith","label":"孤魂野鬼"}
A105: simian_chuge | B105: 四面楚歌 | C105: 个人任务 | D105: 门客 | E105: task_simian_chuge_hanxin_boss | F105: 1 | G105: 韩信 | H105: 奇策突袭 | I105: 10 | J105: 100 | K105: 0.28 | L105: data/mission_templates.yaml:L1007:enemy_guests | M105: {"key":"task_simian_chuge_hanxin_boss","label":"韩信","skills":["stratagem_burst"]}
A106: simian_chuge | B106: 四面楚歌 | C106: 个人任务 | D106: 门客 | E106: task_simian_chuge_pengyue_boss | F106: 1 | G106: 彭越·垓下 | H106: 倾城一击 | I106: 10 | J106: 100 | K106: 0.28 | L106: data/mission_templates.yaml:L1007:enemy_guests | M106: {"key":"task_simian_chuge_pengyue_boss","skills":["city_felling_strike"]}
A107: simian_chuge | B107: 四面楚歌 | C107: 个人任务 | D107: 门客 | E107: task_simian_chuge_yingbu_boss | F107: 1 | G107: 英布·垓下 | H107: 倾城一击 | I107: 10 | J107: 100 | K107: 0.28 | L107: data/mission_templates.yaml:L1007:enemy_guests | M107: {"key":"task_simian_chuge_yingbu_boss","skills":["city_felling_strike"]}
A108: simian_chuge | B108: 四面楚歌 | C108: 个人任务 | D108: 护院 | E108: dao_sheng | F108: 500 | G108: 刀圣 | I108: 10 | L108: data/mission_templates.yaml:L1007:enemy_troops | M108: {"dao_sheng":500}
A109: simian_chuge | B109: 四面楚歌 | C109: 个人任务 | D109: 护院 | E109: qiang_wang | F109: 500 | G109: 枪王 | I109: 10 | L109: data/mission_templates.yaml:L1007:enemy_troops | M109: {"qiang_wang":500}
A110: manzu_ruqin | B110: 蛮族入侵 | C110: 个人任务 | D110: 门客 | E110: task_barbarian_chanyu | F110: 1 | G110: 单于 | H110: 使用模板默认技能 | I110: 10 | J110: 100 | K110: 0.5 | L110: data/mission_templates.yaml:L1046:enemy_guests | M110: {"key":"task_barbarian_chanyu","label":"单于"}
A111: manzu_ruqin | B111: 蛮族入侵 | C111: 个人任务 | D111: 护院 | E111: qiang_wang | F111: 1500 | G111: 枪王 | I111: 10 | L111: data/mission_templates.yaml:L1046:enemy_troops | M111: {"qiang_wang":1500}
A112: zhuiji_manzu | B112: 追击蛮族 | C112: 个人任务 | D112: 门客 | E112: task_barbarian_chanyu | F112: 1 | G112: 单于 | H112: 使用模板默认技能 | I112: 10 | J112: 100 | K112: 0.26 | L112: data/mission_templates.yaml:L1075:enemy_guests | M112: {"key":"task_barbarian_chanyu","label":"单于"}
A113: zhuiji_manzu | B113: 追击蛮族 | C113: 个人任务 | D113: 护院 | E113: qiang_wang | F113: 1000 | G113: 枪王 | I113: 10 | L113: data/mission_templates.yaml:L1075:enemy_troops | M113: {"qiang_wang":1000}
A114: liangshanbo_zhuyingtai | B114: 梁山伯与祝英台 | C114: 个人任务 | D114: 门客 | E114: orig_ma_wencai | F114: 1 | G114: 马文才 | H114: 奇策突袭 | I114: 5 | J114: 60 | K114: 0.16 | L114: data/mission_templates.yaml:L1108:enemy_guests | M114: {"key":"orig_ma_wencai","label":"马文才","skills":["stratagem_burst"]}
A115: liangshanbo_zhuyingtai | B115: 梁山伯与祝英台 | C115: 个人任务 | D115: 护院 | E115: qiang_wang | F115: 200 | G115: 枪王 | I115: 5 | L115: data/mission_templates.yaml:L1108:enemy_troops | M115: {"qiang_wang":200}
A116: liangshanbo_zhuyingtai | B116: 梁山伯与祝英台 | C116: 个人任务 | D116: 护院 | E116: arrow_god | F116: 200 | G116: 箭神 | I116: 5 | L116: data/mission_templates.yaml:L1108:enemy_troops | M116: {"arrow_god":200}
A117: liangshanbo_zhuyingtai | B117: 梁山伯与祝英台 | C117: 个人任务 | D117: 护院 | E117: dao_sheng | F117: 200 | G117: 刀圣 | I117: 5 | L117: data/mission_templates.yaml:L1108:enemy_troops | M117: {"dao_sheng":200}
A118: biyou_candeng | B118: 封神之战：碧游残灯 | C118: 个人任务 | D118: 门客 | E118: task_wanxian_nangong_lie | F118: 1 | G118: 南宫烈 | H118: 使用模板默认技能 | I118: 10 | J118: 88 | K118: 0.34 | L118: data/mission_templates.yaml:L1158:enemy_guests | M118: "task_wanxian_nangong_lie"
A119: biyou_candeng | B119: 封神之战：碧游残灯 | C119: 个人任务 | D119: 门客 | E119: task_wanxian_lu_xuanqing | F119: 1 | G119: 陆玄清 | H119: 使用模板默认技能 | I119: 10 | J119: 88 | K119: 0.34 | L119: data/mission_templates.yaml:L1158:enemy_guests | M119: "task_wanxian_lu_xuanqing"
A120: biyou_candeng | B120: 封神之战：碧游残灯 | C120: 个人任务 | D120: 门客 | E120: task_wanxian_baihe_fushi | F120: 1 | G120: 白鹤符使 | H120: 使用模板默认技能 | I120: 10 | J120: 88 | K120: 0.34 | L120: data/mission_templates.yaml:L1158:enemy_guests | M120: "task_wanxian_baihe_fushi"
A121: biyou_candeng | B121: 封神之战：碧游残灯 | C121: 个人任务 | D121: 门客 | E121: task_wanxian_zhuxian_canfeng | F121: 1 | G121: 诛仙残锋 | H121: 使用模板默认技能 | I121: 10 | J121: 88 | K121: 0.34 | L121: data/mission_templates.yaml:L1158:enemy_guests | M121: "task_wanxian_zhuxian_canfeng"
A122: biyou_candeng | B122: 封神之战：碧游残灯 | C122: 个人任务 | D122: 门客 | E122: task_wanxian_yuzhu | F122: 1 | G122: 余烛 | H122: 使用模板默认技能 | I122: 10 | J122: 88 | K122: 0.34 | L122: data/mission_templates.yaml:L1158:enemy_guests | M122: "task_wanxian_yuzhu"
A123: biyou_candeng | B123: 封神之战：碧游残灯 | C123: 个人任务 | D123: 门客 | E123: task_wanxian_qingsuan_fuzhao | F123: 1 | G123: 清算符诏 | H123: 使用模板默认技能 | I123: 10 | J123: 88 | K123: 0.34 | L123: data/mission_templates.yaml:L1158:enemy_guests | M123: "task_wanxian_qingsuan_fuzhao"
A124: biyou_candeng | B124: 封神之战：碧游残灯 | C124: 个人任务 | D124: 护院 | E124: dao_sheng | F124: 700 | G124: 刀圣 | I124: 10 | L124: data/mission_templates.yaml:L1158:enemy_troops | M124: {"dao_sheng":700}
A125: biyou_candeng | B125: 封神之战：碧游残灯 | C125: 个人任务 | D125: 护院 | E125: qiang_wang | F125: 650 | G125: 枪王 | I125: 10 | L125: data/mission_templates.yaml:L1158:enemy_troops | M125: {"qiang_wang":650}
A126: biyou_candeng | B126: 封神之战：碧游残灯 | C126: 个人任务 | D126: 护院 | E126: arrow_god | F126: 500 | G126: 箭神 | I126: 10 | L126: data/mission_templates.yaml:L1158:enemy_troops | M126: {"arrow_god":500}
...

Sheet 页面展示配置
A1: 任务key | B1: 任务名称 | C1: 物品key | D1: 物品名称 | E1: 原始展示值(JSON) | F1: 用途说明 | G1: 数据来源

Sheet 动态奖励规则
A1: 适用范围 | B1: 奖励规则 | C1: 物品key/取值来源 | D1: 奖励物品 | E1: 计算口径 | F1: 数量说明 | G1: 发奖条件 | H1: 代码来源
A2: 改版前已有散装奖励战报（不含任务宝箱） | B2: 经验果：阵亡护院 | C2: experience_fruit | D2: 经验果 | E2: 双方阵亡护院数量×该兵种招募基准秒数/3600×0.1求和；排除门客及城防单位 | F2: 与阵亡门客贡献合并后向下取整，无固定保底数量 | G2: 玩家一方胜利，非撤退，返程结算 | H2: gameplay/services/battle_salvage.py:_calculate_troop_exp_fruit；gameplay/services/missions_impl/finalization_helpers.py:build_mission_drops_with_salvage
A3: 改版前已有散装奖励战报（不含任务宝箱） | B3: 经验果：阵亡门客 | C3: experience_fruit | D3: 经验果 | E3: 双方remaining_hp=0的门客：等级×稀有度倍率×初始血量/最大血量×0.05求和 | F3: 与阵亡护院贡献合并后向下取整；稀有度倍率见PVPConstants.RARITY_EXP_MULTIPLIER | G3: 玩家一方胜利，非撤退，返程结算 | H3: gameplay/services/battle_salvage.py:_member_exp_fruit；gameplay/constants.py:PVPConstants.RARITY_EXP_MULTIPLIER
A4: 改版前已有散装奖励战报（不含任务宝箱） | B4: 己方阵亡护院装备回收 | C4: 取己方兵种recruit.equipment | D4: 己方兵种招募装备 | E4: 仅己方阵亡护院；每名阵亡护院、每件招募装备独立以20%概率回收1件 | F4: 依实际己方兵种、阵亡数量及战报种子计算；未作为固定配置池写入掉落明细 | G4: 玩家一方胜利，非撤退，返程结算 | H4: gameplay/services/battle_salvage.py:_calculate_equipment_recovery；gameplay/constants.py:PVPConstants.EQUIPMENT_RECOVERY_CHANCE
A5: 全部帮会任务 | B5: 无个人战损回收奖励 | E5: auto_reward=False，仅确定发放配置红宝石至帮会仓库 | F5: 不将战报预览掉落解释为参与者收益 | G5: 帮会胜利后结算 | H5: guilds/services/guild_missions.py:finalize_guild_mission_run
A6: 32新版个人任务 | B6: 经验与装备统一收入宝箱 | C6: 对应mission_chest_* | D6: 宝箱内容 | E6: 按每箱配置发奖；不再额外散发战损经验/装备 | F6: 见宝箱养成预算 | G6: 胜利非撤退得箱；玩家仓库开启 | H6: gameplay/services/missions_impl/finalization_helpers.py；gameplay/services/inventory/use.py

Sheet 统计
A1: 统计项 | B1: 值
A2: 个人任务数 | B2: =COUNTIF(任务列表!$Q$2:$Q$36,"个人任务") -> 32
A3: 帮会任务数 | B3: =COUNTIF(任务列表!$Q$2:$Q$36,"帮会任务") -> 3
A4: 任务总数 | B4: =COUNTA(任务列表!B2:B36) -> 35
A5: 奖励掉落明细行数 | B5: =COUNTA(任务掉落明细!B2:B66) -> 65
A6: 初级任务数 | B6: =COUNTIF(任务列表!$D$2:$D$36,"初级") -> 9
A7: 中级任务数 | B7: =COUNTIF(任务列表!$D$2:$D$36,"中级") -> 11
A8: 高级任务数 | B8: =COUNTIF(任务列表!$D$2:$D$36,"高级") -> 15
A9: 生成时间 | B9: 2026-10-01
A10: 数据范围 | B10: 当前工作区配置，未读取运行中数据库；含全部个人任务及帮会任务。

Sheet 字段说明
A1: 字段/Sheet | B1: 说明
A2: 任务列表 | B2: 每行一个任务。每日次数适用于个人任务，每周次数适用于每帮会每个任务模板；空白表示不适用。
A3: 奖励掉落范围 | B3: 新版个人任务直接发银两与宝箱；内部奖励见新增宝箱奖励明细。旧战报回收见动态奖励规则。帮会公共红宝石机制保留。
A4: 发奖条件 | B4: 个人任务必须玩家一方胜利、非撤退，在返程结算发奖；防守玩家为defender，普通出征为attacker。
A5: 帮会奖励 | B5: 帮会任务胜利后红宝石进入帮会仓库，参与者不会因此直接获得同数量红宝石。当前任务结算未发现额外个人贡献度或个人物品奖励。
A6: 随机池 | B6: 一个池触发后按候选权重随机选一项；权重不是概率。明细将每个候选展开，实际概率及期望数量通过Excel公式计算。
A7: 同物品多条掉落 | B7: 每个drop_table条目独立判定并累加；例如广寒宫月饼存在保底与多个额外概率档，不应将这些档位当作互斥奖励。
A8: 页面展示配置 | B8: probability_drop_table仅影响页面展示，单独列页保留原始值；不参与实际奖励或期望数量计算。guaranteed_drops是页面生成变量，非另一张发奖配置表。
A9: 实际概率 | B9: 仅表示一次胜利后对应条目的配置层发放概率，不包含挑战胜率或开放日期。不同条目的期望数量可相加，但至少获得一件的概率不能简单相加。
A10: 基础耗时 | B10: 个人base_travel_time未填按导入默认1800秒；进攻用于单程修正后再加返程，防守使用一次基准。实际受敏捷及时间倍率影响，不将配置秒数宣称实际耗时。帮会base_duration_seconds受时间倍率缩放，无额外返程。
A11: 发起消耗 | B11: 个人任务每次发起扣10行动点，另消耗entry_cost中的库存物品；行动点列与入场物品列分别展示。帮会任务行动点列为空，不套用个人任务规则。
A12: 个人任务默认值 | B12: daily_limit=3，mission_card_daily_limit=5，display_order=1000，guest_only=False，is_defense=False；未填available_weekdays表示每日开放。
... A18: 规则核对代码 | B18: common/utils/loot.py；gameplay/management/commands/load_mission_templates.py；gameplay/services/missions_impl/finalize_command.py；guilds/services/guild_missions.py。

Sheet 宝箱奖励明细
A1: 任务key | B1: 任务名称 | C1: 宝箱key | D1: 宝箱名称 | E1: 奖励组 | F1: 物品key | G1: 物品名称 | H1: 品质 | I1: 类型 | J1: 组命中概率 | K1: 池内权重 | L1: 权重合计 | M1: 最少数量 | N1: 最多数量 | O1: 单项实际概率 | P1: 平均数量 | Q1: 每箱期望数量 | R1: 单件经验(小时) | S1: 每箱经验期望(小时) | T1: 所需锻造等级 | U1: 图纸产物 | V1: 配置来源
A2: mid_autumn_moon_palace_trial | B2: 广寒宫试炼 | C2: mission_chest_mid_autumn_moon_palace_trial | D2: 广寒宫试炼宝箱 | E2: 必得 | F2: experience_fruit | G2: 经验果 | H2: green | I2: experience_items | J2: 1 | K2: 1 | L2: 1 | M2: 20 | N2: 20 | O2: =J2*K2/L2 -> 1 | P2: =(M2+N2)/2 -> 20 | Q2: =O2*P2 -> 20 | R2: 1 | S2: =Q2*R2 -> 20 | V2: data/item_templates.yaml:mission_chest_mid_autumn_moon_palace_trial.effect_payload
A3: mid_autumn_moon_palace_trial | B3: 广寒宫试炼 | C3: mission_chest_mid_autumn_moon_palace_trial | D3: 广寒宫试炼宝箱 | E3: 必得 | F3: mid_autumn_mooncake | G3: 月饼 | H3: green | I3: loot_box | J3: 1 | K3: 1 | L3: 1 | M3: 1 | N3: 1 | O3: =J3*K3/L3 -> 1 | P3: =(M3+N3)/2 -> 1 | Q3: =O3*P3 -> 1 | R3: 0 | S3: =Q3*R3 -> 0 | V3: data/item_templates.yaml:mission_chest_mid_autumn_moon_palace_trial.effect_payload
A4: mid_autumn_moon_palace_trial | B4: 广寒宫试炼 | C4: mission_chest_mid_autumn_moon_palace_trial | D4: 广寒宫试炼宝箱 | E4: 必得 | F4: buxuedan | G4: 补血丹 | H4: black | I4: medicine | J4: 1 | K4: 1 | L4: 1 | M4: 2 | N4: 2 | O4: =J4*K4/L4 -> 1 | P4: =(M4+N4)/2 -> 2 | Q4: =O4*P4 -> 2 | R4: 0 | S4: =Q4*R4 -> 0 | V4: data/item_templates.yaml:mission_chest_mid_autumn_moon_palace_trial.effect_payload
A5: mid_autumn_moon_palace_trial | B5: 广寒宫试炼 | C5: mission_chest_mid_autumn_moon_palace_trial | D5: 广寒宫试炼宝箱 | E5: mid_autumn_mooncake_bonus_1 | F5: mid_autumn_mooncake | G5: 月饼 | H5: green | I5: loot_box | J5: 0.55 | K5: 1 | L5: 1 | M5: 1 | N5: 1 | O5: =J5*K5/L5 -> 0.55 | P5: =(M5+N5)/2 -> 1 | Q5: =O5*P5 -> 0.55 | R5: 0 | S5: =Q5*R5 -> 0 | V5: data/item_templates.yaml:mission_chest_mid_autumn_moon_palace_trial.effect_payload
A6: mid_autumn_moon_palace_trial | B6: 广寒宫试炼 | C6: mission_chest_mid_autumn_moon_palace_trial | D6: 广寒宫试炼宝箱 | E6: mid_autumn_mooncake_bonus_2 | F6: mid_autumn_mooncake | G6: 月饼 | H6: green | I6: loot_box | J6: 0.25 | K6: 1 | L6: 1 | M6: 2 | N6: 2 | O6: =J6*K6/L6 -> 0.25 | P6: =(M6+N6)/2 -> 2 | Q6: =O6*P6 -> 0.5 | R6: 0 | S6: =Q6*R6 -> 0 | V6: data/item_templates.yaml:mission_chest_mid_autumn_moon_palace_trial.effect_payload
A7: mid_autumn_moon_palace_trial | B7: 广寒宫试炼 | C7: mission_chest_mid_autumn_moon_palace_trial | D7: 广寒宫试炼宝箱 | E7: mid_autumn_mooncake_bonus_4 | F7: mid_autumn_mooncake | G7: 月饼 | H7: green | I7: loot_box | J7: 0.08 | K7: 1 | L7: 1 | M7: 4 | N7: 4 | O7: =J7*K7/L7 -> 0.08 | P7: =(M7+N7)/2 -> 4 | Q7: =O7*P7 -> 0.32 | R7: 0 | S7: =Q7*R7 -> 0 | V7: data/item_templates.yaml:mission_chest_mid_autumn_moon_palace_trial.effect_payload
A8: mid_autumn_moon_palace_trial | B8: 广寒宫试炼 | C8: mission_chest_mid_autumn_moon_palace_trial | D8: 广寒宫试炼宝箱 | E8: mid_autumn_mooncake_bonus_10 | F8: mid_autumn_mooncake | G8: 月饼 | H8: green | I8: loot_box | J8: 0.015 | K8: 1 | L8: 1 | M8: 10 | N8: 10 | O8: =J8*K8/L8 -> 0.015 | P8: =(M8+N8)/2 -> 10 | Q8: =O8*P8 -> 0.15 | R8: 0 | S8: =Q8*R8 -> 0 | V8: data/item_templates.yaml:mission_chest_mid_autumn_moon_palace_trial.effect_payload
A9: mid_autumn_moon_palace_trial | B9: 广寒宫试炼 | C9: mission_chest_mid_autumn_moon_palace_trial | D9: 广寒宫试炼宝箱 | E9: jade_rabbit_summon_scroll | F9: jade_rabbit_summon_scroll | G9: 玉兔召唤卷轴 | H9: green | I9: tool | J9: 0.08 | K9: 1 | L9: 1 | M9: 1 | N9: 1 | O9: =J9*K9/L9 -> 0.08 | P9: =(M9+N9)/2 -> 1 | Q9: =O9*P9 -> 0.08 | R9: 0 | S9: =Q9*R9 -> 0 | V9: data/item_templates.yaml:mission_chest_mid_autumn_moon_palace_trial.effect_payload
A10: mid_autumn_moon_palace_trial | B10: 广寒宫试炼 | C10: mission_chest_mid_autumn_moon_palace_trial | D10: 广寒宫试炼宝箱 | E10: wu_gang_summon_scroll | F10: wu_gang_summon_scroll | G10: 吴刚召唤卷轴 | H10: blue | I10: tool | J10: 0.05 | K10: 1 | L10: 1 | M10: 1 | N10: 1 | O10: =J10*K10/L10 -> 0.05 | P10: =(M10+N10)/2 -> 1 | Q10: =O10*P10 -> 0.05 | R10: 0 | S10: =Q10*R10 -> 0 | V10: data/item_templates.yaml:mission_chest_mid_autumn_moon_palace_trial.effect_payload
A11: mid_autumn_moon_palace_trial | B11: 广寒宫试炼 | C11: mission_chest_mid_autumn_moon_palace_trial | D11: 广寒宫试炼宝箱 | E11: chang_e_summon_scroll | F11: chang_e_summon_scroll | G11: 嫦娥召唤卷轴 | H11: purple | I11: tool | J11: 0.03 | K11: 1 | L11: 1 | M11: 1 | N11: 1 | O11: =J11*K11/L11 -> 0.03 | P11: =(M11+N11)/2 -> 1 | Q11: =O11*P11 -> 0.03 | R11: 0 | S11: =Q11*R11 -> 0 | V11: data/item_templates.yaml:mission_chest_mid_autumn_moon_palace_trial.effect_payload
A12: kasukabe_daisakusen | B12: 春日部大作战 | C12: mission_chest_kasukabe_daisakusen | D12: 春日部大作战宝箱 | E12: 必得 | F12: experience_fruit | G12: 经验果 | H12: green | I12: experience_items | J12: 1 | K12: 1 | L12: 1 | M12: 77 | N12: 77 | O12: =J12*K12/L12 -> 1 | P12: =(M12+N12)/2 -> 77 | Q12: =O12*P12 -> 77 | R12: 1 | S12: =Q12*R12 -> 77 | V12: data/item_templates.yaml:mission_chest_kasukabe_daisakusen.effect_payload
A13: kasukabe_daisakusen | B13: 春日部大作战 | C13: mission_chest_kasukabe_daisakusen | D13: 春日部大作战宝箱 | E13: 必得 | F13: kasukabe_crayon | G13: 小新的蜡笔 | H13: blue | I13: tool | J13: 1 | K13: 1 | L13: 1 | M13: 1 | N13: 1 | O13: =J13*K13/L13 -> 1 | P13: =(M13+N13)/2 -> 1 | Q13: =O13*P13 -> 1 | R13: 0 | S13: =Q13*R13 -> 0 | V13: data/item_templates.yaml:mission_chest_kasukabe_daisakusen.effect_payload
... A115: shanhaiguan | B115: 山海关 | C115: mission_chest_shanhaiguan | D115: 山海关宝箱 | E115: shanhaiguan_skill_book_random | F115: book_last_chance_revival | G115: 《绝处逢生》秘术 | H115: blue | I115: skill_book | J115: 0.09 | K115: 4 | L115: 9 | M115: 1 | N115: 1 | O115: =J115*K115/L115 -> 0.04 | P115: =(M115+N115)/2 -> 1 | Q115: =O115*P115 -> 0.04 | R115: 0 | S115: =Q115*R115 -> 0 | V115: data/item_templates.yaml:mission_chest_shanhaiguan.effect_payload
A116: shanhaiguan | B116: 山海关 | C116: mission_chest_shanhaiguan | D116: 山海关宝箱 | E116: blueprint_xiaowei_set | F116: blueprint_xiaoweitoukie | G116: 校尉头盔图纸 | H116: blue | I116: tool | J116: 0.35 | K116: 1 | L116: 4 | M116: 1 | N116: 1 | O116: =J116*K116/L116 -> 0.0875 | P116: =(M116+N116)/2 -> 1 | Q116: =O116*P116 -> 0.0875 | R116: 0 | S116: =Q116*R116 -> 0 | T116: 5 | U116: 校尉头盔 | V116: data/item_templates.yaml:mission_chest_shanhaiguan.effect_payload
A117: shanhaiguan | B117: 山海关 | C117: mission_chest_shanhaiguan | D117: 山海关宝箱 | E117: blueprint_xiaowei_set | F117: blueprint_xiaoweikaijia | G117: 校尉铠甲图纸 | H117: blue | I117: tool | J117: 0.35 | K117: 1 | L117: 4 | M117: 1 | N117: 1 | O117: =J117*K117/L117 -> 0.0875 | P117: =(M117+N117)/2 -> 1 | Q117: =O117*P117 -> 0.0875 | R117: 0 | S117: =Q117*R117 -> 0 | T117: 5 | U117: 校尉铠甲 | V117: data/item_templates.yaml:mission_chest_shanhaiguan.effect_payload
A118: shanhaiguan | B118: 山海关 | C118: mission_chest_shanhaiguan | D118: 山海关宝箱 | E118: blueprint_xiaowei_set | F118: blueprint_xiaoweichangxue | G118: 校尉长靴图纸 | H118: blue | I118: tool | J118: 0.35 | K118: 1 | L118: 4 | M118: 1 | N118: 1 | O118: =J118*K118/L118 -> 0.0875 | P118: =(M118+N118)/2 -> 1 | Q118: =O118*P118 -> 0.0875 | R118: 0 | S118: =Q118*R118 -> 0 | T118: 5 | U118: 校尉长靴 | V118: data/item_templates.yaml:mission_chest_shanhaiguan.effect_payload
A119: shanhaiguan | B119: 山海关 | C119: mission_chest_shanhaiguan | D119: 山海关宝箱 | E119: blueprint_xiaowei_set | F119: blueprint_xiaoweichangjian | G119: 校尉长剑图纸 | H119: blue | I119: tool | J119: 0.35 | K119: 1 | L119: 4 | M119: 1 | N119: 1 | O119: =J119*K119/L119 -> 0.0875 | P119: =(M119+N119)/2 -> 1 | Q119: =O119*P119 -> 0.0875 | R119: 0 | S119: =Q119*R119 -> 0 | T119: 5 | U119: 校尉长剑 | V119: data/item_templates.yaml:mission_chest_shanhaiguan.effect_payload
A120: shanhaiguan | B120: 山海关 | C120: mission_chest_shanhaiguan | D120: 山海关宝箱 | E120: 守关坐骑 | F120: equip_zhaoyeyushizi | G120: 照夜玉狮子 | H120: blue | I120: equip_mount | J120: 0.35 | K120: 15 | L120: 35 | M120: 1 | N120: 1 | O120: =J120*K120/L120 -> 0.15 | P120: =(M120+N120)/2 -> 1 | Q120: =O120*P120 -> 0.15 | R120: 0 | S120: =Q120*R120 -> 0 | V120: data/item_templates.yaml:mission_chest_shanhaiguan.effect_payload
A121: shanhaiguan | B121: 山海关 | C121: mission_chest_shanhaiguan | D121: 山海关宝箱 | E121: 守关坐骑 | F121: equip_zhuidian | G121: 追电 | H121: blue | I121: equip_mount | J121: 0.35 | K121: 10 | L121: 35 | M121: 1 | N121: 1 | O121: =J121*K121/L121 -> 0.1 | P121: =(M121+N121)/2 -> 1 | Q121: =O121*P121 -> 0.1 | R121: 0 | S121: =Q121*R121 -> 0 | V121: data/item_templates.yaml:mission_chest_shanhaiguan.effect_payload
A122: shanhaiguan | B122: 山海关 | C122: mission_chest_shanhaiguan | D122: 山海关宝箱 | E122: 守关坐骑 | F122: equip_bailongju | G122: 白龙驹 | H122: blue | I122: equip_mount | J122: 0.35 | K122: 8 | L122: 35 | M122: 1 | N122: 1 | O122: =J122*K122/L122 -> 0.08 | P122: =(M122+N122)/2 -> 1 | Q122: =O122*P122 -> 0.08 | R122: 0 | S122: =Q122*R122 -> 0 | V122: data/item_templates.yaml:mission_chest_shanhaiguan.effect_payload
A123: shanhaiguan | B123: 山海关 | C123: mission_chest_shanhaiguan | D123: 山海关宝箱 | E123: 守关坐骑 | F123: equip_dilu | G123: 的卢 | H123: purple | I123: equip_mount | J123: 0.35 | K123: 2 | L123: 35 | M123: 1 | N123: 1 | O123: =J123*K123/L123 -> 0.02 | P123: =(M123+N123)/2 -> 1 | Q123: =O123*P123 -> 0.02 | R123: 0 | S123: =Q123*R123 -> 0 | V123: data/item_templates.yaml:mission_chest_shanhaiguan.effect_payload
A124: shanhaiguan | B124: 山海关 | C124: mission_chest_shanhaiguan | D124: 山海关宝箱 | E124: 主题装备 | F124: equip_luopan | G124: 罗盘 | H124: green | I124: equip_ornament | J124: 0.4 | K124: 10000 | L124: 40000 | M124: 1 | N124: 1 | O124: =J124*K124/L124 -> 0.1 | P124: =(M124+N124)/2 -> 1 | Q124: =O124*P124 -> 0.1 | R124: 0 | S124: =Q124*R124 -> 0 | V124: data/item_templates.yaml:mission_chest_shanhaiguan.effect_payload
A125: shanhaiguan | B125: 山海关 | C125: mission_chest_shanhaiguan | D125: 山海关宝箱 | E125: 主题装备 | F125: equip_tiehufu | G125: 铁护符 | H125: green | I125: equip_ornament | J125: 0.4 | K125: 10000 | L125: 40000 | M125: 1 | N125: 1 | O125: =J125*K125/L125 -> 0.1 | P125: =(M125+N125)/2 -> 1 | Q125: =O125*P125 -> 0.1 | R125: 0 | S125: =Q125*R125 -> 0 | V125: data/item_templates.yaml:mission_chest_shanhaiguan.effect_payload
A126: shanhaiguan | B126: 山海关 | C126: mission_chest_shanhaiguan | D126: 山海关宝箱 | E126: 主题装备 | F126: equip_feiyukui | G126: 飞羽盔 | H126: blue | I126: equip_helmet | J126: 0.4 | K126: 10000 | L126: 40000 | M126: 1 | N126: 1 | O126: =J126*K126/L126 -> 0.1 | P126: =(M126+N126)/2 -> 1 | Q126: =O126*P126 -> 0.1 | R126: 0 | S126: =Q126*R126 -> 0 | V126: data/item_templates.yaml:mission_chest_shanhaiguan.effect_payload
A127: shanhaiguan | B127: 山海关 | C127: mission_chest_shanhaiguan | D127: 山海关宝箱 | E127: 主题装备 | F127: equip_langyakui | G127: 狼牙盔 | H127: blue | I127: equip_helmet | J127: 0.4 | K127: 10000 | L127: 40000 | M127: 1 | N127: 1 | O127: =J127*K127/L127 -> 0.1 | P127: =(M127+N127)/2 -> 1 | Q127: =O127*P127 -> 0.1 | R127: 0 | S127: =Q127*R127 -> 0 | V127: data/item_templates.yaml:mission_chest_shanhaiguan.effect_payload
A128: shiren_daochang | B128: 十人道场 | C128: mission_chest_shiren_daochang | D128: 十人道场宝箱 | E128: 必得 | F128: experience_fruit | G128: 经验果 | H128: green | I128: experience_items | J128: 1 | K128: 1 | L128: 1 | M128: 38 | N128: 38 | O128: =J128*K128/L128 -> 1 | P128: =(M128+N128)/2 -> 38 | Q128: =O128*P128 -> 38 | R128: 1 | S128: =Q128*R128 -> 38 | V128: data/item_templates.yaml:mission_chest_shiren_daochang.effect_payload
A129: shiren_daochang | B129: 十人道场 | C129: mission_chest_shiren_daochang | D129: 十人道场宝箱 | E129: 必得 | F129: experience_peach | G129: 经验桃子 | H129: green | I129: experience_items | J129: 1 | K129: 1 | L129: 1 | M129: 9 | N129: 9 | O129: =J129*K129/L129 -> 1 | P129: =(M129+N129)/2 -> 9 | Q129: =O129*P129 -> 9 | R129: 8 | S129: =Q129*R129 -> 72 | V129: data/item_templates.yaml:mission_chest_shiren_daochang.effect_payload
A130: shiren_daochang | B130: 十人道场 | C130: mission_chest_shiren_daochang | D130: 十人道场宝箱 | E130: 必得 | F130: buxuedan | G130: 补血丹 | H130: black | I130: medicine | J130: 1 | K130: 1 | L130: 1 | M130: 2 | N130: 2 | O130: =J130*K130/L130 -> 1 | P130: =(M130+N130)/2 -> 2 | Q130: =O130*P130 -> 2 | R130: 0 | S130: =Q130*R130 -> 0 | V130: data/item_templates.yaml:mission_chest_shiren_daochang.effect_payload
A131: shiren_daochang | B131: 十人道场 | C131: mission_chest_shiren_daochang | D131: 十人道场宝箱 | E131: 必得 | F131: tong | G131: 铜 | H131: black | I131: resource | J131: 1 | K131: 1 | L131: 1 | M131: 8 | N131: 8 | O131: =J131*K131/L131 -> 1 | P131: =(M131+N131)/2 -> 8 | Q131: =O131*P131 -> 8 | R131: 0 | S131: =Q131*R131 -> 0 | V131: data/item_templates.yaml:mission_chest_shiren_daochang.effect_payload
... A146: jiguanshou_chuxian | B146: 机关兽初现 | C146: mission_chest_jiguanshou_chuxian | D146: 机关兽初现宝箱 | E146: 必得 | F146: tie | G146: 铁 | H146: black | I146: resource | J146: 1 | K146: 1 | L146: 1 | M146: 1 | N146: 1 | O146: =J146*K146/L146 -> 1 | P146: =(M146+N146)/2 -> 1 | Q146: =O146*P146 -> 1 | R146: 0 | S146: =Q146*R146 -> 0 | V146: data/item_templates.yaml:mission_chest_jiguanshou_chuxian.effect_payload
A147: jiguanshou_chuxian | B147: 机关兽初现 | C147: mission_chest_jiguanshou_chuxian | D147: 机关兽初现宝箱 | E147: 机关入门 | F147: blueprint_xiaoxingjiguanshu | G147: 小型机关鼠图纸 | H147: green | I147: tool | J147: 0.8 | K147: 3 | L147: 10 | M147: 1 | N147: 1 | O147: =J147*K147/L147 -> 0.24 | P147: =(M147+N147)/2 -> 1 | Q147: =O147*P147 -> 0.24 | R147: 0 | S147: =Q147*R147 -> 0 | T147: 6 | U147: 小型机关鼠 | V147: data/item_templates.yaml:mission_chest_jiguanshou_chuxian.effect_payload
A148: jiguanshou_chuxian | B148: 机关兽初现 | C148: mission_chest_jiguanshou_chuxian | D148: 机关兽初现宝箱 | E148: 机关入门 | F148: blueprint_tongchanjiguan | G148: 铜蝉机关图纸 | H148: green | I148: tool | J148: 0.8 | K148: 3 | L148: 10 | M148: 1 | N148: 1 | O148: =J148*K148/L148 -> 0.24 | P148: =(M148+N148)/2 -> 1 | Q148: =O148*P148 -> 0.24 | R148: 0 | S148: =Q148*R148 -> 0 | T148: 6 | U148: 铜蝉机关 | V148: data/item_templates.yaml:mission_chest_jiguanshou_chuxian.effect_payload
A149: jiguanshou_chuxian | B149: 机关兽初现 | C149: mission_chest_jiguanshou_chuxian | D149: 机关兽初现宝箱 | E149: 机关入门 | F149: blueprint_jixiemao | G149: 机械猫图纸 | H149: blue | I149: tool | J149: 0.8 | K149: 1 | L149: 10 | M149: 1 | N149: 1 | O149: =J149*K149/L149 -> 0.08 | P149: =(M149+N149)/2 -> 1 | Q149: =O149*P149 -> 0.08 | R149: 0 | S149: =Q149*R149 -> 0 | T149: 8 | U149: 机械猫 | V149: data/item_templates.yaml:mission_chest_jiguanshou_chuxian.effect_payload
A150: jiguanshou_chuxian | B150: 机关兽初现 | C150: mission_chest_jiguanshou_chuxian | D150: 机关兽初现宝箱 | E150: 机关入门 | F150: equip_qingtongsuanchou | G150: 青铜算筹 | H150: green | I150: equip_ornament | J150: 0.8 | K150: 3 | L150: 10 | M150: 1 | N150: 1 | O150: =J150*K150/L150 -> 0.24 | P150: =(M150+N150)/2 -> 1 | Q150: =O150*P150 -> 0.24 | R150: 0 | S150: =Q150*R150 -> 0 | V150: data/item_templates.yaml:mission_chest_jiguanshou_chuxian.effect_payload
A151: jiguanshou_chuxian | B151: 机关兽初现 | C151: mission_chest_jiguanshou_chuxian | D151: 机关兽初现宝箱 | E151: 随小型机关鼠图纸附带（同次命中） | F151: tong | G151: 铜 | H151: black | I151: resource | J151: 0.24 | K151: 1 | L151: 1 | M151: 17 | N151: 17 | O151: =J151*K151/L151 -> 0.24 | P151: =(M151+N151)/2 -> 17 | Q151: =O151*P151 -> 4.08 | R151: 0 | S151: =Q151*R151 -> 0 | V151: data/item_templates.yaml:mission_chest_jiguanshou_chuxian.effect_payload
A152: jiguanshou_chuxian | B152: 机关兽初现 | C152: mission_chest_jiguanshou_chuxian | D152: 机关兽初现宝箱 | E152: 随小型机关鼠图纸附带（同次命中） | F152: xi | G152: 锡 | H152: black | I152: resource | J152: 0.24 | K152: 1 | L152: 1 | M152: 11 | N152: 11 | O152: =J152*K152/L152 -> 0.24 | P152: =(M152+N152)/2 -> 11 | Q152: =O152*P152 -> 2.64 | R152: 0 | S152: =Q152*R152 -> 0 | V152: data/item_templates.yaml:mission_chest_jiguanshou_chuxian.effect_payload
A153: jiguanshou_chuxian | B153: 机关兽初现 | C153: mission_chest_jiguanshou_chuxian | D153: 机关兽初现宝箱 | E153: 随小型机关鼠图纸附带（同次命中） | F153: tie | G153: 铁 | H153: black | I153: resource | J153: 0.24 | K153: 1 | L153: 1 | M153: 8 | N153: 8 | O153: =J153*K153/L153 -> 0.24 | P153: =(M153+N153)/2 -> 8 | Q153: =O153*P153 -> 1.92 | R153: 0 | S153: =Q153*R153 -> 0 | V153: data/item_templates.yaml:mission_chest_jiguanshou_chuxian.effect_payload
A154: jiguanshou_chuxian | B154: 机关兽初现 | C154: mission_chest_jiguanshou_chuxian | D154: 机关兽初现宝箱 | E154: 随小型机关鼠图纸附带（同次命中） | F154: wood_essence | G154: 木质精华 | H154: green | I154: resource | J154: 0.24 | K154: 1 | L154: 1 | M154: 1 | N154: 1 | O154: =J154*K154/L154 -> 0.24 | P154: =(M154+N154)/2 -> 1 | Q154: =O154*P154 -> 0.24 | R154: 0 | S154: =Q154*R154 -> 0 | V154: data/item_templates.yaml:mission_chest_jiguanshou_chuxian.effect_payload
A155: jiguanshou_chuxian | B155: 机关兽初现 | C155: mission_chest_jiguanshou_chuxian | D155: 机关兽初现宝箱 | E155: 随小型机关鼠图纸附带（同次命中） | F155: copper_essence | G155: 铜质精华 | H155: green | I155: resource | J155: 0.24 | K155: 1 | L155: 1 | M155: 1 | N155: 1 | O155: =J155*K155/L155 -> 0.24 | P155: =(M155+N155)/2 -> 1 | Q155: =O155*P155 -> 0.24 | R155: 0 | S155: =Q155*R155 -> 0 | V155: data/item_templates.yaml:mission_chest_jiguanshou_chuxian.effect_payload
A156: jiguanshou_chuxian | B156: 机关兽初现 | C156: mission_chest_jiguanshou_chuxian | D156: 机关兽初现宝箱 | E156: 随小型机关鼠图纸附带（同次命中） | F156: shuiqumu | G156: 水曲木 | H156: black | I156: resource | J156: 0.24 | K156: 1 | L156: 1 | M156: 4 | N156: 4 | O156: =J156*K156/L156 -> 0.24 | P156: =(M156+N156)/2 -> 4 | Q156: =O156*P156 -> 0.96 | R156: 0 | S156: =Q156*R156 -> 0 | V156: data/item_templates.yaml:mission_chest_jiguanshou_chuxian.effect_payload
A157: jiguanshou_chuxian | B157: 机关兽初现 | C157: mission_chest_jiguanshou_chuxian | D157: 机关兽初现宝箱 | E157: 随小型机关鼠图纸附带（同次命中） | F157: tiemu | G157: 铁木 | H157: green | I157: resource | J157: 0.24 | K157: 1 | L157: 1 | M157: 1 | N157: 1 | O157: =J157*K157/L157 -> 0.24 | P157: =(M157+N157)/2 -> 1 | Q157: =O157*P157 -> 0.24 | R157: 0 | S157: =Q157*R157 -> 0 | V157: data/item_templates.yaml:mission_chest_jiguanshou_chuxian.effect_payload
A158: jiguanshou_chuxian | B158: 机关兽初现 | C158: mission_chest_jiguanshou_chuxian | D158: 机关兽初现宝箱 | E158: 随小型机关鼠图纸附带（同次命中） | F158: jingangmei | G158: 金刚煤 | H158: green | I158: resource | J158: 0.24 | K158: 1 | L158: 1 | M158: 1 | N158: 1 | O158: =J158*K158/L158 -> 0.24 | P158: =(M158+N158)/2 -> 1 | Q158: =O158*P158 -> 0.24 | R158: 0 | S158: =Q158*R158 -> 0 | V158: data/item_templates.yaml:mission_chest_jiguanshou_chuxian.effect_payload
A159: jiguanshou_chuxian | B159: 机关兽初现 | C159: mission_chest_jiguanshou_chuxian | D159: 机关兽初现宝箱 | E159: 随小型机关鼠图纸附带（同次命中） | F159: paozi | G159: 刨子 | H159: black | I159: resource | J159: 0.24 | K159: 1 | L159: 1 | M159: 2 | N159: 2 | O159: =J159*K159/L159 -> 0.24 | P159: =(M159+N159)/2 -> 2 | Q159: =O159*P159 -> 0.48 | R159: 0 | S159: =Q159*R159 -> 0 | V159: data/item_templates.yaml:mission_chest_jiguanshou_chuxian.effect_payload
A160: jiguanshou_chuxian | B160: 机关兽初现 | C160: mission_chest_jiguanshou_chuxian | D160: 机关兽初现宝箱 | E160: 随小型机关鼠图纸附带（同次命中） | F160: zaozi | G160: 凿子 | H160: black | I160: resource | J160: 0.24 | K160: 1 | L160: 1 | M160: 1 | N160: 1 | O160: =J160*K160/L160 -> 0.24 | P160: =(M160+N160)/2 -> 1 | Q160: =O160*P160 -> 0.24 | R160: 0 | S160: =Q160*R160 -> 0 | V160: data/item_templates.yaml:mission_chest_jiguanshou_chuxian.effect_payload
A161: jiguanshou_chuxian | B161: 机关兽初现 | C161: mission_chest_jiguanshou_chuxian | D161: 机关兽初现宝箱 | E161: 随小型机关鼠图纸附带（同次命中） | F161: air_stone | G161: 空气之石 | H161: blue | I161: resource | J161: 0.24 | K161: 1 | L161: 1 | M161: 1 | N161: 1 | O161: =J161*K161/L161 -> 0.24 | P161: =(M161+N161)/2 -> 1 | Q161: =O161*P161 -> 0.24 | R161: 0 | S161: =Q161*R161 -> 0 | V161: data/item_templates.yaml:mission_chest_jiguanshou_chuxian.effect_payload
... A192: biwu_zhaoqin | B192: 比武招亲 | C192: mission_chest_biwu_zhaoqin | D192: 比武招亲宝箱 | E192: book_endless_chatter | F192: book_endless_chatter | G192: 《唧唧歪歪》秘术 | H192: green | I192: skill_book | J192: 0.05 | K192: 1 | L192: 1 | M192: 1 | N192: 1 | O192: =J192*K192/L192 -> 0.05 | P192: =(M192+N192)/2 -> 1 | Q192: =O192*P192 -> 0.05 | R192: 0 | S192: =Q192*R192 -> 0 | V192: data/item_templates.yaml:mission_chest_biwu_zhaoqin.effect_payload
A193: biwu_zhaoqin | B193: 比武招亲 | C193: mission_chest_biwu_zhaoqin | D193: 比武招亲宝箱 | E193: blueprint_jiguanxiong | F193: blueprint_jiguanxiong | G193: 机关熊图纸 | H193: purple | I193: tool | J193: 0.05 | K193: 1 | L193: 1 | M193: 1 | N193: 1 | O193: =J193*K193/L193 -> 0.05 | P193: =(M193+N193)/2 -> 1 | Q193: =O193*P193 -> 0.05 | R193: 0 | S193: =Q193*R193 -> 0 | T193: 10 | U193: 机关熊 | V193: data/item_templates.yaml:mission_chest_biwu_zhaoqin.effect_payload
A194: biwu_zhaoqin | B194: 比武招亲 | C194: mission_chest_biwu_zhaoqin | D194: 比武招亲宝箱 | E194: biwu_equipment_pool | F194: equip_xuantiejia | G194: 玄铁甲 | H194: green | I194: equip_armor | J194: 0.8 | K194: 1 | L194: 4 | M194: 1 | N194: 1 | O194: =J194*K194/L194 -> 0.2 | P194: =(M194+N194)/2 -> 1 | Q194: =O194*P194 -> 0.2 | R194: 0 | S194: =Q194*R194 -> 0 | V194: data/item_templates.yaml:mission_chest_biwu_zhaoqin.effect_payload
A195: biwu_zhaoqin | B195: 比武招亲 | C195: mission_chest_biwu_zhaoqin | D195: 比武招亲宝箱 | E195: biwu_equipment_pool | F195: equip_qingtongsuanchou | G195: 青铜算筹 | H195: green | I195: equip_ornament | J195: 0.8 | K195: 1 | L195: 4 | M195: 1 | N195: 1 | O195: =J195*K195/L195 -> 0.2 | P195: =(M195+N195)/2 -> 1 | Q195: =O195*P195 -> 0.2 | R195: 0 | S195: =Q195*R195 -> 0 | V195: data/item_templates.yaml:mission_chest_biwu_zhaoqin.effect_payload
A196: biwu_zhaoqin | B196: 比武招亲 | C196: mission_chest_biwu_zhaoqin | D196: 比武招亲宝箱 | E196: biwu_equipment_pool | F196: equip_tongjing | G196: 铜镜 | H196: green | I196: equip_ornament | J196: 0.8 | K196: 1 | L196: 4 | M196: 1 | N196: 1 | O196: =J196*K196/L196 -> 0.2 | P196: =(M196+N196)/2 -> 1 | Q196: =O196*P196 -> 0.2 | R196: 0 | S196: =Q196*R196 -> 0 | V196: data/item_templates.yaml:mission_chest_biwu_zhaoqin.effect_payload
A197: biwu_zhaoqin | B197: 比武招亲 | C197: mission_chest_biwu_zhaoqin | D197: 比武招亲宝箱 | E197: biwu_equipment_pool | F197: equip_qingzongma | G197: 青鬃马 | H197: green | I197: equip_mount | J197: 0.8 | K197: 1 | L197: 4 | M197: 1 | N197: 1 | O197: =J197*K197/L197 -> 0.2 | P197: =(M197+N197)/2 -> 1 | Q197: =O197*P197 -> 0.2 | R197: 0 | S197: =Q197*R197 -> 0 | V197: data/item_templates.yaml:mission_chest_biwu_zhaoqin.effect_payload
A198: biwu_zhaoqin | B198: 比武招亲 | C198: mission_chest_biwu_zhaoqin | D198: 比武招亲宝箱 | E198: 随机关熊图纸附带（同次命中） | F198: tong | G198: 铜 | H198: black | I198: resource | J198: 0.05 | K198: 1 | L198: 1 | M198: 34 | N198: 34 | O198: =J198*K198/L198 -> 0.05 | P198: =(M198+N198)/2 -> 34 | Q198: =O198*P198 -> 1.7 | R198: 0 | S198: =Q198*R198 -> 0 | V198: data/item_templates.yaml:mission_chest_biwu_zhaoqin.effect_payload
A199: biwu_zhaoqin | B199: 比武招亲 | C199: mission_chest_biwu_zhaoqin | D199: 比武招亲宝箱 | E199: 随机关熊图纸附带（同次命中） | F199: xi | G199: 锡 | H199: black | I199: resource | J199: 0.05 | K199: 1 | L199: 1 | M199: 23 | N199: 23 | O199: =J199*K199/L199 -> 0.05 | P199: =(M199+N199)/2 -> 23 | Q199: =O199*P199 -> 1.15 | R199: 0 | S199: =Q199*R199 -> 0 | V199: data/item_templates.yaml:mission_chest_biwu_zhaoqin.effect_payload
A200: biwu_zhaoqin | B200: 比武招亲 | C200: mission_chest_biwu_zhaoqin | D200: 比武招亲宝箱 | E200: 随机关熊图纸附带（同次命中） | F200: tie | G200: 铁 | H200: black | I200: resource | J200: 0.05 | K200: 1 | L200: 1 | M200: 18 | N200: 18 | O200: =J200*K200/L200 -> 0.05 | P200: =(M200+N200)/2 -> 18 | Q200: =O200*P200 -> 0.9 | R200: 0 | S200: =Q200*R200 -> 0 | V200: data/item_templates.yaml:mission_chest_biwu_zhaoqin.effect_payload
A201: biwu_zhaoqin | B201: 比武招亲 | C201: mission_chest_biwu_zhaoqin | D201: 比武招亲宝箱 | E201: 随机关熊图纸附带（同次命中） | F201: wood_essence | G201: 木质精华 | H201: green | I201: resource | J201: 0.05 | K201: 1 | L201: 1 | M201: 1 | N201: 1 | O201: =J201*K201/L201 -> 0.05 | P201: =(M201+N201)/2 -> 1 | Q201: =O201*P201 -> 0.05 | R201: 0 | S201: =Q201*R201 -> 0 | V201: data/item_templates.yaml:mission_chest_biwu_zhaoqin.effect_payload
A202: biwu_zhaoqin | B202: 比武招亲 | C202: mission_chest_biwu_zhaoqin | D202: 比武招亲宝箱 | E202: 随机关熊图纸附带（同次命中） | F202: copper_essence | G202: 铜质精华 | H202: green | I202: resource | J202: 0.05 | K202: 1 | L202: 1 | M202: 2 | N202: 2 | O202: =J202*K202/L202 -> 0.05 | P202: =(M202+N202)/2 -> 2 | Q202: =O202*P202 -> 0.1 | R202: 0 | S202: =Q202*R202 -> 0 | V202: data/item_templates.yaml:mission_chest_biwu_zhaoqin.effect_payload
A203: biwu_zhaoqin | B203: 比武招亲 | C203: mission_chest_biwu_zhaoqin | D203: 比武招亲宝箱 | E203: 随机关熊图纸附带（同次命中） | F203: xuan_tie_essence | G203: 玄铁精华 | H203: blue | I203: resource | J203: 0.05 | K203: 1 | L203: 1 | M203: 1 | N203: 1 | O203: =J203*K203/L203 -> 0.05 | P203: =(M203+N203)/2 -> 1 | Q203: =O203*P203 -> 0.05 | R203: 0 | S203: =Q203*R203 -> 0 | V203: data/item_templates.yaml:mission_chest_biwu_zhaoqin.effect_payload
A204: biwu_zhaoqin | B204: 比武招亲 | C204: mission_chest_biwu_zhaoqin | D204: 比武招亲宝箱 | E204: 随机关熊图纸附带（同次命中） | F204: zitanmu | G204: 紫檀木 | H204: green | I204: resource | J204: 0.05 | K204: 1 | L204: 1 | M204: 2 | N204: 2 | O204: =J204*K204/L204 -> 0.05 | P204: =(M204+N204)/2 -> 2 | Q204: =O204*P204 -> 0.1 | R204: 0 | S204: =Q204*R204 -> 0 | V204: data/item_templates.yaml:mission_chest_biwu_zhaoqin.effect_payload
A205: biwu_zhaoqin | B205: 比武招亲 | C205: mission_chest_biwu_zhaoqin | D205: 比武招亲宝箱 | E205: 随机关熊图纸附带（同次命中） | F205: tiemu | G205: 铁木 | H205: green | I205: resource | J205: 0.05 | K205: 1 | L205: 1 | M205: 7 | N205: 7 | O205: =J205*K205/L205 -> 0.05 | P205: =(M205+N205)/2 -> 7 | Q205: =O205*P205 -> 0.35 | R205: 0 | S205: =Q205*R205 -> 0 | V205: data/item_templates.yaml:mission_chest_biwu_zhaoqin.effect_payload
... A227: tianpeng_dijiao_2 | B227: 天蓬元帅的地窖（第二层） | C227: mission_chest_tianpeng_dijiao_2 | D227: 天蓬地窖二层宝箱 | E227: experience_pineapple | F227: experience_pineapple | G227: 经验菠萝 | H227: blue | I227: experience_items | J227: 0.99 | K227: 1 | L227: 1 | M227: 20 | N227: 20 | O227: =J227*K227/L227 -> 0.99 | P227: =(M227+N227)/2 -> 20 | Q227: =O227*P227 -> 19.8 | R227: 16 | S227: =Q227*R227 -> 316.8 | V227: data/item_templates.yaml:mission_chest_tianpeng_dijiao_2.effect_payload
A228: tianpeng_dijiao_2 | B228: 天蓬元帅的地窖（第二层） | C228: mission_chest_tianpeng_dijiao_2 | D228: 天蓬地窖二层宝箱 | E228: blueprint_huxianjian | F228: blueprint_huxianjian | G228: 狐仙剑图纸 | H228: purple | I228: tool | J228: 0.05 | K228: 1 | L228: 1 | M228: 1 | N228: 1 | O228: =J228*K228/L228 -> 0.05 | P228: =(M228+N228)/2 -> 1 | Q228: =O228*P228 -> 0.05 | R228: 0 | S228: =Q228*R228 -> 0 | T228: 7 | U228: 狐仙剑 | V228: data/item_templates.yaml:mission_chest_tianpeng_dijiao_2.effect_payload
A229: tianpeng_dijiao_2 | B229: 天蓬元帅的地窖（第二层） | C229: mission_chest_tianpeng_dijiao_2 | D229: 天蓬地窖二层宝箱 | E229: blueprint_huxianpao | F229: blueprint_huxianpao | G229: 狐仙袍图纸 | H229: purple | I229: tool | J229: 0.1 | K229: 1 | L229: 1 | M229: 1 | N229: 1 | O229: =J229*K229/L229 -> 0.1 | P229: =(M229+N229)/2 -> 1 | Q229: =O229*P229 -> 0.1 | R229: 0 | S229: =Q229*R229 -> 0 | T229: 7 | U229: 狐仙袍 | V229: data/item_templates.yaml:mission_chest_tianpeng_dijiao_2.effect_payload
A230: tianpeng_dijiao_2 | B230: 天蓬元帅的地窖（第二层） | C230: mission_chest_tianpeng_dijiao_2 | D230: 天蓬地窖二层宝箱 | E230: blueprint_huxianxie | F230: blueprint_huxianxie | G230: 狐仙鞋图纸 | H230: purple | I230: tool | J230: 0.1 | K230: 1 | L230: 1 | M230: 1 | N230: 1 | O230: =J230*K230/L230 -> 0.1 | P230: =(M230+N230)/2 -> 1 | Q230: =O230*P230 -> 0.1 | R230: 0 | S230: =Q230*R230 -> 0 | T230: 7 | U230: 狐仙鞋 | V230: data/item_templates.yaml:mission_chest_tianpeng_dijiao_2.effect_payload
A231: tianpeng_dijiao_2 | B231: 天蓬元帅的地窖（第二层） | C231: mission_chest_tianpeng_dijiao_2 | D231: 天蓬地窖二层宝箱 | E231: 主题装备 | F231: equip_zhaoyaojing | G231: 照妖镜 | H231: blue | I231: equip_ornament | J231: 0.55 | K231: 15000 | L231: 55000 | M231: 1 | N231: 1 | O231: =J231*K231/L231 -> 0.15 | P231: =(M231+N231)/2 -> 1 | Q231: =O231*P231 -> 0.15 | R231: 0 | S231: =Q231*R231 -> 0 | V231: data/item_templates.yaml:mission_chest_tianpeng_dijiao_2.effect_payload
A232: tianpeng_dijiao_2 | B232: 天蓬元帅的地窖（第二层） | C232: mission_chest_tianpeng_dijiao_2 | D232: 天蓬地窖二层宝箱 | E232: 主题装备 | F232: equip_qiankunquan | G232: 乾坤圈 | H232: blue | I232: equip_ornament | J232: 0.55 | K232: 10000 | L232: 55000 | M232: 1 | N232: 1 | O232: =J232*K232/L232 -> 0.1 | P232: =(M232+N232)/2 -> 1 | Q232: =O232*P232 -> 0.1 | R232: 0 | S232: =Q232*R232 -> 0 | V232: data/item_templates.yaml:mission_chest_tianpeng_dijiao_2.effect_payload
A233: tianpeng_dijiao_2 | B233: 天蓬元帅的地窖（第二层） | C233: mission_chest_tianpeng_dijiao_2 | D233: 天蓬地窖二层宝箱 | E233: 主题装备 | F233: equip_tianjiluopan | G233: 天机罗盘 | H233: blue | I233: equip_ornament | J233: 0.55 | K233: 10000 | L233: 55000 | M233: 1 | N233: 1 | O233: =J233*K233/L233 -> 0.1 | P233: =(M233+N233)/2 -> 1 | Q233: =O233*P233 -> 0.1 | R233: 0 | S233: =Q233*R233 -> 0 | V233: data/item_templates.yaml:mission_chest_tianpeng_dijiao_2.effect_payload
A234: tianpeng_dijiao_2 | B234: 天蓬元帅的地窖（第二层） | C234: mission_chest_tianpeng_dijiao_2 | D234: 天蓬地窖二层宝箱 | E234: 主题装备 | F234: equip_lingwenyubi | G234: 灵纹玉笔 | H234: blue | I234: equip_ornament | J234: 0.55 | K234: 10000 | L234: 55000 | M234: 1 | N234: 1 | O234: =J234*K234/L234 -> 0.1 | P234: =(M234+N234)/2 -> 1 | Q234: =O234*P234 -> 0.1 | R234: 0 | S234: =Q234*R234 -> 0 | V234: data/item_templates.yaml:mission_chest_tianpeng_dijiao_2.effect_payload
A235: tianpeng_dijiao_2 | B235: 天蓬元帅的地窖（第二层） | C235: mission_chest_tianpeng_dijiao_2 | D235: 天蓬地窖二层宝箱 | E235: 主题装备 | F235: equip_guanxingdeng | G235: 观星灯 | H235: blue | I235: equip_ornament | J235: 0.55 | K235: 10000 | L235: 55000 | M235: 1 | N235: 1 | O235: =J235*K235/L235 -> 0.1 | P235: =(M235+N235)/2 -> 1 | Q235: =O235*P235 -> 0.1 | R235: 0 | S235: =Q235*R235 -> 0 | V235: data/item_templates.yaml:mission_chest_tianpeng_dijiao_2.effect_payload
A236: jiguan_chuniao | B236: 机关雏鸟 | C236: mission_chest_jiguan_chuniao | D236: 机关雏鸟宝箱 | E236: 必得 | F236: experience_fruit | G236: 经验果 | H236: green | I236: experience_items | J236: 1 | K236: 1 | L236: 1 | M236: 28 | N236: 28 | O236: =J236*K236/L236 -> 1 | P236: =(M236+N236)/2 -> 28 | Q236: =O236*P236 -> 28 | R236: 1 | S236: =Q236*R236 -> 28 | V236: data/item_templates.yaml:mission_chest_jiguan_chuniao.effect_payload
A237: jiguan_chuniao | B237: 机关雏鸟 | C237: mission_chest_jiguan_chuniao | D237: 机关雏鸟宝箱 | E237: 必得 | F237: buxuedan | G237: 补血丹 | H237: black | I237: medicine | J237: 1 | K237: 1 | L237: 1 | M237: 2 | N237: 2 | O237: =J237*K237/L237 -> 1 | P237: =(M237+N237)/2 -> 2 | Q237: =O237*P237 -> 2 | R237: 0 | S237: =Q237*R237 -> 0 | V237: data/item_templates.yaml:mission_chest_jiguan_chuniao.effect_payload
A238: jiguan_chuniao | B238: 机关雏鸟 | C238: mission_chest_jiguan_chuniao | D238: 机关雏鸟宝箱 | E238: 必得 | F238: tong | G238: 铜 | H238: black | I238: resource | J238: 1 | K238: 1 | L238: 1 | M238: 8 | N238: 8 | O238: =J238*K238/L238 -> 1 | P238: =(M238+N238)/2 -> 8 | Q238: =O238*P238 -> 8 | R238: 0 | S238: =Q238*R238 -> 0 | V238: data/item_templates.yaml:mission_chest_jiguan_chuniao.effect_payload
A239: jiguan_chuniao | B239: 机关雏鸟 | C239: mission_chest_jiguan_chuniao | D239: 机关雏鸟宝箱 | E239: 必得 | F239: xi | G239: 锡 | H239: black | I239: resource | J239: 1 | K239: 1 | L239: 1 | M239: 5 | N239: 5 | O239: =J239*K239/L239 -> 1 | P239: =(M239+N239)/2 -> 5 | Q239: =O239*P239 -> 5 | R239: 0 | S239: =Q239*R239 -> 0 | V239: data/item_templates.yaml:mission_chest_jiguan_chuniao.effect_payload
A240: jiguan_chuniao | B240: 机关雏鸟 | C240: mission_chest_jiguan_chuniao | D240: 机关雏鸟宝箱 | E240: 必得 | F240: tie | G240: 铁 | H240: black | I240: resource | J240: 1 | K240: 1 | L240: 1 | M240: 3 | N240: 3 | O240: =J240*K240/L240 -> 1 | P240: =(M240+N240)/2 -> 3 | Q240: =O240*P240 -> 3 | R240: 0 | S240: =Q240*R240 -> 0 | V240: data/item_templates.yaml:mission_chest_jiguan_chuniao.effect_payload
A241: jiguan_chuniao | B241: 机关雏鸟 | C241: mission_chest_jiguan_chuniao | D241: 机关雏鸟宝箱 | E241: book_thunder_nine_heavens | F241: book_thunder_nine_heavens | G241: 《雷动九天》秘术 | H241: blue | I241: skill_book | J241: 0.04 | K241: 1 | L241: 1 | M241: 1 | N241: 1 | O241: =J241*K241/L241 -> 0.04 | P241: =(M241+N241)/2 -> 1 | Q241: =O241*P241 -> 0.04 | R241: 0 | S241: =Q241*R241 -> 0 | V241: data/item_templates.yaml:mission_chest_jiguan_chuniao.effect_payload
A242: jiguan_chuniao | B242: 机关雏鸟 | C242: mission_chest_jiguan_chuniao | D242: 机关雏鸟宝箱 | E242: 主题装备 | F242: equip_feiyunzui | G242: 飞云锥 | H242: blue | I242: equip_mount | J242: 0.15 | K242: 10000 | L242: 15000 | M242: 1 | N242: 1 | O242: =J242*K242/L242 -> 0.1 | P242: =(M242+N242)/2 -> 1 | Q242: =O242*P242 -> 0.1 | R242: 0 | S242: =Q242*R242 -> 0 | V242: data/item_templates.yaml:mission_chest_jiguan_chuniao.effect_payload
A243: jiguan_chuniao | B243: 机关雏鸟 | C243: mission_chest_jiguan_chuniao | D243: 机关雏鸟宝箱 | E243: 主题装备 | F243: equip_luopan | G243: 罗盘 | H243: green | I243: equip_ornament | J243: 0.15 | K243: 5000 | L243: 15000 | M243: 1 | N243: 1 | O243: =J243*K243/L243 -> 0.05 | P243: =(M243+N243)/2 -> 1 | Q243: =O243*P243 -> 0.05 | R243: 0 | S243: =Q243*R243 -> 0 | V243: data/item_templates.yaml:mission_chest_jiguan_chuniao.effect_payload
A244: jiguan_chuniao | B244: 机关雏鸟 | C244: mission_chest_jiguan_chuniao | D244: 机关雏鸟宝箱 | E244: 机关雏鸟主图纸 | F244: blueprint_jiguanchuniao | G244: 机关雏鸟图纸 | H244: blue | I244: tool | J244: 0.4 | K244: 1 | L244: 1 | M244: 1 | N244: 1 | O244: =J244*K244/L244 -> 0.4 | P244: =(M244+N244)/2 -> 1 | Q244: =O244*P244 -> 0.4 | R244: 0 | S244: =Q244*R244 -> 0 | T244: 8 | U244: 机关雏鸟 | V244: data/item_templates.yaml:mission_chest_jiguan_chuniao.effect_payload
A245: jiguan_chuniao | B245: 机关雏鸟 | C245: mission_chest_jiguan_chuniao | D245: 机关雏鸟宝箱 | E245: blueprint_mechanism_blue | F245: blueprint_jixiemao | G245: 机械猫图纸 | H245: blue | I245: tool | J245: 0.2 | K245: 1 | L245: 3 | M245: 1 | N245: 1 | O245: =J245*K245/L245 -> 0.066666667 | P245: =(M245+N245)/2 -> 1 | Q245: =O245*P245 -> 0.066666667 | R245: 0 | S245: =Q245*R245 -> 0 | T245: 8 | U245: 机械猫 | V245: data/item_templates.yaml:mission_chest_jiguan_chuniao.effect_payload
A246: jiguan_chuniao | B246: 机关雏鸟 | C246: mission_chest_jiguan_chuniao | D246: 机关雏鸟宝箱 | E246: blueprint_mechanism_blue | F246: blueprint_kuileimuren | G246: 傀儡木人图纸 | H246: blue | I246: tool | J246: 0.2 | K246: 1 | L246: 3 | M246: 1 | N246: 1 | O246: =J246*K246/L246 -> 0.066666667 | P246: =(M246+N246)/2 -> 1 | Q246: =O246*P246 -> 0.066666667 | R246: 0 | S246: =Q246*R246 -> 0 | T246: 8 | U246: 傀儡木人 | V246: data/item_templates.yaml:mission_chest_jiguan_chuniao.effect_payload
A247: jiguan_chuniao | B247: 机关雏鸟 | C247: mission_chest_jiguan_chuniao | D247: 机关雏鸟宝箱 | E247: blueprint_mechanism_blue | F247: blueprint_qingji | G247: 庆忌图纸 | H247: blue | I247: tool | J247: 0.2 | K247: 1 | L247: 3 | M247: 1 | N247: 1 | O247: =J247*K247/L247 -> 0.066666667 | P247: =(M247+N247)/2 -> 1 | Q247: =O247*P247 -> 0.066666667 | R247: 0 | S247: =Q247*R247 -> 0 | T247: 8 | U247: 庆忌 | V247: data/item_templates.yaml:mission_chest_jiguan_chuniao.effect_payload
A248: jiguan_chuniao | B248: 机关雏鸟 | C248: mission_chest_jiguan_chuniao | D248: 机关雏鸟宝箱 | E248: 随机关雏鸟图纸附带（同次命中） | F248: tong | G248: 铜 | H248: black | I248: resource | J248: 0.4 | K248: 1 | L248: 1 | M248: 25 | N248: 25 | O248: =J248*K248/L248 -> 0.4 | P248: =(M248+N248)/2 -> 25 | Q248: =O248*P248 -> 10 | R248: 0 | S248: =Q248*R248 -> 0 | V248: data/item_templates.yaml:mission_chest_jiguan_chuniao.effect_payload
A249: jiguan_chuniao | B249: 机关雏鸟 | C249: mission_chest_jiguan_chuniao | D249: 机关雏鸟宝箱 | E249: 随机关雏鸟图纸附带（同次命中） | F249: xi | G249: 锡 | H249: black | I249: resource | J249: 0.4 | K249: 1 | L249: 1 | M249: 17 | N249: 17 | O249: =J249*K249/L249 -> 0.4 | P249: =(M249+N249)/2 -> 17 | Q249: =O249*P249 -> 6.8 | R249: 0 | S249: =Q249*R249 -> 0 | V249: data/item_templates.yaml:mission_chest_jiguan_chuniao.effect_payload
A250: jiguan_chuniao | B250: 机关雏鸟 | C250: mission_chest_jiguan_chuniao | D250: 机关雏鸟宝箱 | E250: 随机关雏鸟图纸附带（同次命中） | F250: tie | G250: 铁 | H250: black | I250: resource | J250: 0.4 | K250: 1 | L250: 1 | M250: 12 | N250: 12 | O250: =J250*K250/L250 -> 0.4 | P250: =(M250+N250)/2 -> 12 | Q250: =O250*P250 -> 4.8 | R250: 0 | S250: =Q250*R250 -> 0 | V250: data/item_templates.yaml:mission_chest_jiguan_chuniao.effect_payload
A251: jiguan_chuniao | B251: 机关雏鸟 | C251: mission_chest_jiguan_chuniao | D251: 机关雏鸟宝箱 | E251: 随机关雏鸟图纸附带（同次命中） | F251: wood_essence | G251: 木质精华 | H251: green | I251: resource | J251: 0.4 | K251: 1 | L251: 1 | M251: 1 | N251: 1 | O251: =J251*K251/L251 -> 0.4 | P251: =(M251+N251)/2 -> 1 | Q251: =O251*P251 -> 0.4 | R251: 0 | S251: =Q251*R251 -> 0 | V251: data/item_templates.yaml:mission_chest_jiguan_chuniao.effect_payload
A252: jiguan_chuniao | B252: 机关雏鸟 | C252: mission_chest_jiguan_chuniao | D252: 机关雏鸟宝箱 | E252: 随机关雏鸟图纸附带（同次命中） | F252: copper_essence | G252: 铜质精华 | H252: green | I252: resource | J252: 0.4 | K252: 1 | L252: 1 | M252: 1 | N252: 1 | O252: =J252*K252/L252 -> 0.4 | P252: =(M252+N252)/2 -> 1 | Q252: =O252*P252 -> 0.4 | R252: 0 | S252: =Q252*R252 -> 0 | V252: data/item_templates.yaml:mission_chest_jiguan_chuniao.effect_payload
A253: jiguan_chuniao | B253: 机关雏鸟 | C253: mission_chest_jiguan_chuniao | D253: 机关雏鸟宝箱 | E253: 随机关雏鸟图纸附带（同次命中） | F253: xuan_tie_essence | G253: 玄铁精华 | H253: blue | I253: resource | J253: 0.4 | K253: 1 | L253: 1 | M253: 1 | N253: 1 | O253: =J253*K253/L253 -> 0.4 | P253: =(M253+N253)/2 -> 1 | Q253: =O253*P253 -> 0.4 | R253: 0 | S253: =Q253*R253 -> 0 | V253: data/item_templates.yaml:mission_chest_jiguan_chuniao.effect_payload
A254: jiguan_chuniao | B254: 机关雏鸟 | C254: mission_chest_jiguan_chuniao | D254: 机关雏鸟宝箱 | E254: 随机关雏鸟图纸附带（同次命中） | F254: zitanmu | G254: 紫檀木 | H254: green | I254: resource | J254: 0.4 | K254: 1 | L254: 1 | M254: 2 | N254: 2 | O254: =J254*K254/L254 -> 0.4 | P254: =(M254+N254)/2 -> 2 | Q254: =O254*P254 -> 0.8 | R254: 0 | S254: =Q254*R254 -> 0 | V254: data/item_templates.yaml:mission_chest_jiguan_chuniao.effect_payload
A255: jiguan_chuniao | B255: 机关雏鸟 | C255: mission_chest_jiguan_chuniao | D255: 机关雏鸟宝箱 | E255: 随机关雏鸟图纸附带（同次命中） | F255: shuiqumu | G255: 水曲木 | H255: black | I255: resource | J255: 0.4 | K255: 1 | L255: 1 | M255: 4 | N255: 4 | O255: =J255*K255/L255 -> 0.4 | P255: =(M255+N255)/2 -> 4 | Q255: =O255*P255 -> 1.6 | R255: 0 | S255: =Q255*R255 -> 0 | V255: data/item_templates.yaml:mission_chest_jiguan_chuniao.effect_payload
A256: jiguan_chuniao | B256: 机关雏鸟 | C256: mission_chest_jiguan_chuniao | D256: 机关雏鸟宝箱 | E256: 随机关雏鸟图纸附带（同次命中） | F256: tiemu | G256: 铁木 | H256: green | I256: resource | J256: 0.4 | K256: 1 | L256: 1 | M256: 1 | N256: 1 | O256: =J256*K256/L256 -> 0.4 | P256: =(M256+N256)/2 -> 1 | Q256: =O256*P256 -> 0.4 | R256: 0 | S256: =Q256*R256 -> 0 | V256: data/item_templates.yaml:mission_chest_jiguan_chuniao.effect_payload
A257: jiguan_chuniao | B257: 机关雏鸟 | C257: mission_chest_jiguan_chuniao | D257: 机关雏鸟宝箱 | E257: 随机关雏鸟图纸附带（同次命中） | F257: heiyuanshi | G257: 黑原石 | H257: green | I257: resource | J257: 0.4 | K257: 1 | L257: 1 | M257: 2 | N257: 2 | O257: =J257*K257/L257 -> 0.4 | P257: =(M257+N257)/2 -> 2 | Q257: =O257*P257 -> 0.8 | R257: 0 | S257: =Q257*R257 -> 0 | V257: data/item_templates.yaml:mission_chest_jiguan_chuniao.effect_payload
A258: jiguan_chuniao | B258: 机关雏鸟 | C258: mission_chest_jiguan_chuniao | D258: 机关雏鸟宝箱 | E258: 随机关雏鸟图纸附带（同次命中） | F258: jingangmei | G258: 金刚煤 | H258: green | I258: resource | J258: 0.4 | K258: 1 | L258: 1 | M258: 1 | N258: 1 | O258: =J258*K258/L258 -> 0.4 | P258: =(M258+N258)/2 -> 1 | Q258: =O258*P258 -> 0.4 | R258: 0 | S258: =Q258*R258 -> 0 | V258: data/item_templates.yaml:mission_chest_jiguan_chuniao.effect_payload
A259: jiguan_chuniao | B259: 机关雏鸟 | C259: mission_chest_jiguan_chuniao | D259: 机关雏鸟宝箱 | E259: 随机关雏鸟图纸附带（同次命中） | F259: paozi | G259: 刨子 | H259: black | I259: resource | J259: 0.4 | K259: 1 | L259: 1 | M259: 2 | N259: 2 | O259: =J259*K259/L259 -> 0.4 | P259: =(M259+N259)/2 -> 2 | Q259: =O259*P259 -> 0.8 | R259: 0 | S259: =Q259*R259 -> 0 | V259: data/item_templates.yaml:mission_chest_jiguan_chuniao.effect_payload
... A321: jiufeng_feihuan | B321: 九峰匪患 | C321: mission_chest_jiufeng_feihuan | D321: 九峰匪患宝箱 | E321: 必得 | F321: tie | G321: 铁 | H321: black | I321: resource | J321: 1 | K321: 1 | L321: 1 | M321: 3 | N321: 3 | O321: =J321*K321/L321 -> 1 | P321: =(M321+N321)/2 -> 3 | Q321: =O321*P321 -> 3 | R321: 0 | S321: =Q321*R321 -> 0 | V321: data/item_templates.yaml:mission_chest_jiufeng_feihuan.effect_payload
A322: jiufeng_feihuan | B322: 九峰匪患 | C322: mission_chest_jiufeng_feihuan | D322: 九峰匪患宝箱 | E322: 救援机关 | F322: blueprint_muniuliuma | G322: 木牛流马图纸 | H322: purple | I322: tool | J322: 0.03 | K322: 1 | L322: 1 | M322: 1 | N322: 1 | O322: =J322*K322/L322 -> 0.03 | P322: =(M322+N322)/2 -> 1 | Q322: =O322*P322 -> 0.03 | R322: 0 | S322: =Q322*R322 -> 0 | T322: 10 | U322: 木牛流马 | V322: data/item_templates.yaml:mission_chest_jiufeng_feihuan.effect_payload
A323: jiufeng_feihuan | B323: 九峰匪患 | C323: mission_chest_jiufeng_feihuan | D323: 九峰匪患宝箱 | E323: 主题装备 | F323: equip_yemantoukie | G323: 野蛮头盔 | H323: green | I323: equip_helmet | J323: 0.55 | K323: 10000 | L323: 55000 | M323: 1 | N323: 1 | O323: =J323*K323/L323 -> 0.1 | P323: =(M323+N323)/2 -> 1 | Q323: =O323*P323 -> 0.1 | R323: 0 | S323: =Q323*R323 -> 0 | V323: data/item_templates.yaml:mission_chest_jiufeng_feihuan.effect_payload
A324: jiufeng_feihuan | B324: 九峰匪患 | C324: mission_chest_jiufeng_feihuan | D324: 九峰匪患宝箱 | E324: 主题装备 | F324: equip_yemankandao | G324: 野蛮砍刀 | H324: green | I324: equip_weapon | J324: 0.55 | K324: 10000 | L324: 55000 | M324: 1 | N324: 1 | O324: =J324*K324/L324 -> 0.1 | P324: =(M324+N324)/2 -> 1 | Q324: =O324*P324 -> 0.1 | R324: 0 | S324: =Q324*R324 -> 0 | V324: data/item_templates.yaml:mission_chest_jiufeng_feihuan.effect_payload
A325: jiufeng_feihuan | B325: 九峰匪患 | C325: mission_chest_jiufeng_feihuan | D325: 九峰匪患宝箱 | E325: 主题装备 | F325: equip_zhuifengxue | G325: 追风靴 | H325: blue | I325: equip_shoes | J325: 0.55 | K325: 7000 | L325: 55000 | M325: 1 | N325: 1 | O325: =J325*K325/L325 -> 0.07 | P325: =(M325+N325)/2 -> 1 | Q325: =O325*P325 -> 0.07 | R325: 0 | S325: =Q325*R325 -> 0 | V325: data/item_templates.yaml:mission_chest_jiufeng_feihuan.effect_payload
A326: jiufeng_feihuan | B326: 九峰匪患 | C326: mission_chest_jiufeng_feihuan | D326: 九峰匪患宝箱 | E326: 主题装备 | F326: equip_yingxingxue | G326: 影行靴 | H326: blue | I326: equip_shoes | J326: 0.55 | K326: 7000 | L326: 55000 | M326: 1 | N326: 1 | O326: =J326*K326/L326 -> 0.07 | P326: =(M326+N326)/2 -> 1 | Q326: =O326*P326 -> 0.07 | R326: 0 | S326: =Q326*R326 -> 0 | V326: data/item_templates.yaml:mission_chest_jiufeng_feihuan.effect_payload
A327: jiufeng_feihuan | B327: 九峰匪患 | C327: mission_chest_jiufeng_feihuan | D327: 九峰匪患宝箱 | E327: 主题装备 | F327: equip_pojunxue | G327: 破军靴 | H327: blue | I327: equip_shoes | J327: 0.55 | K327: 6000 | L327: 55000 | M327: 1 | N327: 1 | O327: =J327*K327/L327 -> 0.06 | P327: =(M327+N327)/2 -> 1 | Q327: =O327*P327 -> 0.06 | R327: 0 | S327: =Q327*R327 -> 0 | V327: data/item_templates.yaml:mission_chest_jiufeng_feihuan.effect_payload
...

Sheet 宝箱养成预算
A1: 任务key | B1: 任务名称 | C1: 难度 | D1: 宝箱名称 | E1: 养成定位 | F1: 直接银两 | G1: 开放星期 | H1: 每日基础次数 | I1: 固定经验果 | J1: 原配置经验期望(小时) | K1: 敌军回收参考(小时) | L1: 新箱经验期望(小时) | M1: 较原配置增加(小时) | N1: 入场消耗 | O1: 规则
A2: mid_autumn_moon_palace_trial | B2: 广寒宫试炼 | C2: 中级 | D2: 广寒宫试炼宝箱 | E2: 节日收集：月饼兑换与月宫门客 | F2: 40000 | G2: 2,4,6,7 | H2: 3 | I2: 20 | J2: 0 | K2: 20.666667 | L2: =SUMIF('宝箱奖励明细'!A$2:A$696,A2,'宝箱奖励明细'!S$2:S$696) -> 20 | M2: =L2-J2 -> 20 | N2: {} | O2: 箱不可交易；器械仅图纸；仓容5
A3: kasukabe_daisakusen | B3: 春日部大作战 | C3: 中级 | D3: 春日部大作战宝箱 | E3: 活动收集：蜡笔兑换与动感超人专属装备 | F3: 40000 | G3: 2,4,6,7 | H3: 3 | I3: 77 | J3: 18 | K3: 77.066667 | L3: =SUMIF('宝箱奖励明细'!A$2:A$696,A3,'宝箱奖励明细'!S$2:S$696) -> 95 | M3: =L3-J3 -> 77 | N3: {} | O3: 箱不可交易；器械仅图纸；仓容5
A4: huashan_lunjian | B4: 华山论贱 | C4: 初级 | D4: 华山论贱宝箱 | E4: 新手文武入门：折扇、轻盔与驭雷术 | F4: 8000 | G4: 每日 | H4: 3 | I4: 2 | J4: 0 | K4: 2.4 | L4: =SUMIF('宝箱奖励明细'!A$2:A$696,A4,'宝箱奖励明细'!S$2:S$696) -> 2 | M4: =L4-J4 -> 2 | N4: {} | O4: 箱不可交易；器械仅图纸；仓容5
A5: wagangzhai_nixi | B5: 瓦岗寨的逆袭 | C5: 中级 | D5: 瓦岗寨的逆袭宝箱 | E5: 庄园防守：重甲、军阵饰品与玄甲战驹 | F5: 40000 | G5: 每日 | H5: 3 | I5: 81 | J5: 24 | K5: 81 | L5: =SUMIF('宝箱奖励明细'!A$2:A$696,A5,'宝箱奖励明细'!S$2:S$696) -> 105 | M5: =L5-J5 -> 81 | N5: {} | O5: 箱不可交易；器械仅图纸；仓容5
A6: jingyanggang | B6: 景阳冈 | C6: 初级 | D6: 景阳冈宝箱 | E6: 新手猎虎：虎皮靴与虎纹盔 | F6: 7000 | G6: 每日 | H6: 3 | I6: 1 | J6: 0 | K6: 0.75 | L6: =SUMIF('宝箱奖励明细'!A$2:A$696,A6,'宝箱奖励明细'!S$2:S$696) -> 1 | M6: =L6-J6 -> 1 | N6: {} | O6: 箱不可交易；器械仅图纸；仓容5
A7: wulongshan | B7: 乌龙山 | C7: 初级 | D7: 乌龙山宝箱 | E7: 初期武客：棍、盔、靴与入门坐骑 | F7: 15000 | G7: 每日 | H7: 3 | I7: 4 | J7: 0 | K7: 4.2666667 | L7: =SUMIF('宝箱奖励明细'!A$2:A$696,A7,'宝箱奖励明细'!S$2:S$696) -> 4 | M7: =L7-J7 -> 4 | N7: {} | O7: 箱不可交易；器械仅图纸；仓容5
A8: wagangzhai | B8: 瓦岗寨 | C8: 初级 | D8: 瓦岗寨宝箱 | E8: 初期军阵：甲胄、长兵与军用饰品 | F8: 20000 | G8: 每日 | H8: 3 | I8: 7 | J8: 0 | K8: 7.8 | L8: =SUMIF('宝箱奖励明细'!A$2:A$696,A8,'宝箱奖励明细'!S$2:S$696) -> 7 | M8: =L8-J8 -> 7 | N8: {} | O8: 箱不可交易；器械仅图纸；仓容5
A9: fugui_shanzhuang | B9: 富贵山庄 | C9: 初级 | D9: 富贵山庄宝箱 | E9: 初期文客：文房、玉佩与筹谋秘术 | F9: 14000 | G9: 每日 | H9: 3 | I9: 2 | J9: 0 | K9: 2 | L9: =SUMIF('宝箱奖励明细'!A$2:A$696,A9,'宝箱奖励明细'!S$2:S$696) -> 2 | M9: =L9-J9 -> 2 | N9: {} | O9: 箱不可交易；器械仅图纸；仓容5
A10: shizipo_heidian | B10: 十字坡黑店 | C10: 中级 | D10: 十字坡黑店宝箱 | E10: 中期奇袭：鞭、刀、阴招秘术 | F10: 30000 | G10: 每日 | H10: 3 | I10: 16 | J10: 0 | K10: 16.333333 | L10: =SUMIF('宝箱奖励明细'!A$2:A$696,A10,'宝箱奖励明细'!S$2:S$696) -> 16 | M10: =L10-J10 -> 16 | N10: {} | O10: 箱不可交易；器械仅图纸；仓容5
A11: shanhaiguan | B11: 山海关 | C11: 中级 | D11: 山海关宝箱 | E11: 中期守关：军备图纸、坐骑与守御秘术 | F11: 40000 | G11: 每日 | H11: 3 | I11: 20 | J11: 0 | K11: 20.666667 | L11: =SUMIF('宝箱奖励明细'!A$2:A$696,A11,'宝箱奖励明细'!S$2:S$696) -> 20 | M11: =L11-J11 -> 20 | N11: {} | O11: 箱不可交易；器械仅图纸；仓容5
A12: shiren_daochang | B12: 十人道场 | C12: 中级 | D12: 十人道场宝箱 | E12: 中期经验试炼：法衣、法器与群体秘术 | F12: 20000 | G12: 每日 | H12: 3 | I12: 38 | J12: 72 | K12: 38.5 | L12: =SUMIF('宝箱奖励明细'!A$2:A$696,A12,'宝箱奖励明细'!S$2:S$696) -> 110 | M12: =L12-J12 -> 38 | N12: {} | O12: 箱不可交易；器械仅图纸；仓容5
A13: jiguanshou_chuxian | B13: 机关兽初现 | C13: 初级 | D13: 机关兽初现宝箱 | E13: 机关入门：绿蓝器械图纸与算筹 | F13: 24000 | G13: 每日 | H13: 2 | I13: 28 | J13: 0 | K13: 28 | L13: =SUMIF('宝箱奖励明细'!A$2:A$696,A13,'宝箱奖励明细'!S$2:S$696) -> 28 | M13: =L13-J13 -> 28 | N13: {} | O13: 箱不可交易；器械仅图纸；仓容5
... A33: baimenlou_mingyun_jueze | B33: 飞将浮沉录：白门楼命运抉择 | C33: 高级 | D33: 白门楼宝箱 | E33: 飞将招募终局：吕布貂蝉召唤、易容与破军军备 | F33: 180000 | G33: 每日 | H33: 1 | I33: 177 | J33: 172.8 | K33: 177 | L33: =SUMIF('宝箱奖励明细'!A$2:A$696,A33,'宝箱奖励明细'!S$2:S$696) -> 349.8 | M33: =L33-J33 -> 177 | N33: {"hulao_war_banner": 1} | O33: 箱不可交易；器械仅图纸；仓容5

Sheet 宝箱规则说明
A1: 项目 | B1: 说明
A2: 范围 | B2: 32个人任务；3帮会任务维持公共红宝石奖励。
A3: 发奖 | B3: 玩家胜利且非撤退，在既有结算时机获得原银两+对应宝箱×1；原无银两的分桃、地窖二层仍只奖励宝箱。
A4: 开箱 | B4: 仓库点击使用；保底经验+多个独立奖励组，命中某组只按权重选一项；组间可同时命中。
A5: 经验预算 | B5: 固定经验果取敌方门客全败满血+敌方护院80%阵亡参考向下取整、至少1；保留原配置经验概率和数量。不计玩家损失，不等同旧每场实际收益。
A6: 经验差值 | B6: 新箱减原配置的差值主要是战斗回收归入固定保底；不是凭空新增同等经验。实际新旧差异取决于旧战损。
A7: 器械 | B7: 只得图纸，命中时附带配方每种材料的一半向下取整；剩余材料与锻造等级仍需满足。半材料与图纸同次命中，不是独立抽取。
A8: 活动 | B8: 月饼、蜡笔固定1及55%×1、25%×2、8%×4、1.5%×10独立奖励组保留；单次期望2.52。月饼兼作兑换与开箱道具。
A9: 任务链 | B9: 汜水战报、虎牢战旗、阵旗碎片、玉虚残印在对应箱各必得1，开箱取得凭证后用于下一关。宝箱不可交易。
A10: 兼容 | B10: 已有非空旧掉落战报仍按旧奖励与回收结算；空掉落防守战报沿用领取时当前模板。旧武林箱保留原池/价格/交易/仓容，器械改图纸；新版高级华山用独立箱。
A11: 仓库 | B11: 箱占5；普通任务/开箱奖励沿用仓满仍入库的既有策略，不吞奖励。缺任一奖励候选模板则保留整个宝箱等待同步。
A12: 概率 | B12: 概率不含胜率。EV=组概率×权重/总权重×平均数量。华山85%紫/15%橙互斥保证一件；官渡15%橙与25%紫独立；配套材料随图纸命中。
... A15: 来源 | B15: 工作区YAML配置与结算、开箱源码，2026-10-01；未读取或修改线上数据库。

Sheet 长期目标与兑换
A1: 任务key | B1: 任务名称 | C1: 累积道具 | D1: 兑换装备 | E1: 兑换需要胜利开箱数 | F1: 每箱碎片 | G1: 每日基础次数 | H1: 装备随机概率 | I1: 首次获得期望胜利数（含兑换） | J1: 达到兑换数仍未随机出货概率 | K1: 假设与限制
A2: fengbang_tianmen | B2: 封神之战：封榜天门 | C2: 诛仙剑意 | D2: 诛仙剑 | E2: 30 | F2: 1 | G2: 1 | H2: 0.05 | I2: =(1-(1-H2)^E2)/H2 -> 15.707225 | J2: =(1-H2)^E2 -> 0.21463876 | K2: 胜利并开箱累积；仓库使用兑换；不含战败/缺勤；随机掉落不清空碎片
A3: zhuolu_zhongyuan | B3: 逐鹿中原 | C3: 轩辕剑意 | D3: 轩辕剑 | E3: 40 | F3: 1 | G3: 1 | H3: 0.021428571 | I3: =(1-(1-H3)^E3)/H3 -> 27.046258 | J3: =(1-H3)^E3 -> 0.42043732 | K3: 胜利并开箱累积；仓库使用兑换；不含战败/缺勤；随机掉落不清空碎片
A4: guandu_zhizhan | B4: 官渡之战 | C4: 官渡帝王战章 | D4: 帝王盔 | E4: 40 | F4: 1 | G4: 1 | H4: 0.030612245 | I4: =(1-(1-H4)^E4)/H4 -> 23.24764 | J4: =(1-H4)^E4 -> 0.28833754 | K4: 胜利并开箱累积；仓库使用兑换；不含战败/缺勤；随机掉落不清空碎片
A5: huashan_lunjian_advanced | B5: 华山论剑 | C5: 华山重剑心得 | D5: 玄铁重剑 | E5: 40 | F5: 1 | G5: 1 | H5: 0.015 | I5: =(1-(1-H5)^E5)/H5 -> 30.245156 | J5: =(1-H5)^E5 -> 0.54632267 | K5: 胜利并开箱累积；仓库使用兑换；不含战败/缺勤；随机掉落不清空碎片
A6: hulao_qunying_zhan_lvbu | B6: 飞将浮沉录：虎牢关群英战吕布 | C6: 虎牢画戟战魂 | D6: 方天画戟 | E6: 40 | F6: 1 | G6: 1 | H6: 0.033333333 | I6: =(1-(1-H6)^E6)/H6 -> 22.269796 | J6: =(1-H6)^E6 -> 0.25767348 | K6: 胜利并开箱累积；仓库使用兑换；不含战败/缺勤；随机掉落不清空碎片
A7: baimenlou_mingyun_jueze | B7: 飞将浮沉录：白门楼命运抉择 | C7: 白门楼盘龙战魂 | D7: 盘龙棍 | E7: 40 | F7: 1 | G7: 1 | H7: 0.1 | I7: =(1-(1-H7)^E7)/H7 -> 9.8521912 | J7: =(1-H7)^E7 -> 0.014780883 | K7: 胜利并开箱累积；仓库使用兑换；不含战败/缺勤；随机掉落不清空碎片
